[
  {
    "name": "Absolute Zero",
    "hex": "#0048BA"
  },
  {
    "name": "Acid Grün",
    "hex": "#B0BF1A"
  },
  {
    "name": "Aero",
    "hex": "#7CB9E8"
  },
  {
    "name": "Aero Blau",
    "hex": "#C9FFE5"
  },
  {
    "name": "African Violett",
    "hex": "#B284BE"
  },
  {
    "name": "Air Force Blau (RAF)",
    "hex": "#5D8AA8"
  },
  {
    "name": "Air Force Blau (USAF)",
    "hex": "#00308F"
  },
  {
    "name": "Air Superiority Blau",
    "hex": "#72A0C1"
  },
  {
    "name": "Alabama Karmesin",
    "hex": "#AF002A"
  },
  {
    "name": "Alabaster",
    "hex": "#F2F0E6"
  },
  {
    "name": "Alice Blau",
    "hex": "#F0F8FF"
  },
  {
    "name": "Alien Armpit",
    "hex": "#84DE02"
  },
  {
    "name": "Alizarin Karmesin",
    "hex": "#E32636"
  },
  {
    "name": "Alloy Orange",
    "hex": "#C46210"
  },
  {
    "name": "Almond",
    "hex": "#EFDECD"
  },
  {
    "name": "Amaranth",
    "hex": "#E52B50"
  },
  {
    "name": "Amaranth Tief Lila",
    "hex": "#9F2B68"
  },
  {
    "name": "Amaranth Rosa",
    "hex": "#F19CBB"
  },
  {
    "name": "Amaranth Lila",
    "hex": "#AB274F"
  },
  {
    "name": "Amaranth Rot",
    "hex": "#D3212D"
  },
  {
    "name": "Amazon Store",
    "hex": "#3B7A57"
  },
  {
    "name": "Amazonite",
    "hex": "#00C4B0"
  },
  {
    "name": "Amber",
    "hex": "#FFBF00"
  },
  {
    "name": "Amber (SAE/ECE)",
    "hex": "#FF7E00"
  },
  {
    "name": "American Rose",
    "hex": "#FF033E"
  },
  {
    "name": "Amethyst",
    "hex": "#9966CC"
  },
  {
    "name": "Android Grün",
    "hex": "#A4C639"
  },
  {
    "name": "Anti-Flash Weiß",
    "hex": "#F2F3F4"
  },
  {
    "name": "Antique Brass",
    "hex": "#CD9575"
  },
  {
    "name": "Antique Bronze",
    "hex": "#665D1E"
  },
  {
    "name": "Antique Fuchsia",
    "hex": "#915C83"
  },
  {
    "name": "Antique Rubin",
    "hex": "#841B2D"
  },
  {
    "name": "Antique Weiß",
    "hex": "#FAEBD7"
  },
  {
    "name": "Ao (English)",
    "hex": "#008000"
  },
  {
    "name": "Apple Grün",
    "hex": "#8DB600"
  },
  {
    "name": "Apricot",
    "hex": "#FBCEB1"
  },
  {
    "name": "Aqua",
    "hex": "#00FFFF"
  },
  {
    "name": "Aquamarine",
    "hex": "#7FFFD4"
  },
  {
    "name": "Arctic Lime",
    "hex": "#D0FF14"
  },
  {
    "name": "Army Grün",
    "hex": "#4B5320"
  },
  {
    "name": "Arsenic",
    "hex": "#3B444B"
  },
  {
    "name": "Artichoke",
    "hex": "#8F9779"
  },
  {
    "name": "Arylide Gelb",
    "hex": "#E9D66B"
  },
  {
    "name": "Ash Grau",
    "hex": "#B2BEB5"
  },
  {
    "name": "Asparagus",
    "hex": "#87A96B"
  },
  {
    "name": "Atomic Tangerine",
    "hex": "#FF9966"
  },
  {
    "name": "Auburn",
    "hex": "#A52A2A"
  },
  {
    "name": "Aureolin",
    "hex": "#FDEE00"
  },
  {
    "name": "AuroMetalSaurus",
    "hex": "#6E7F80"
  },
  {
    "name": "Avocado",
    "hex": "#568203"
  },
  {
    "name": "Awesome",
    "hex": "#FF2052"
  },
  {
    "name": "Aztec Gold",
    "hex": "#C39953"
  },
  {
    "name": "Azur",
    "hex": "#007FFF"
  },
  {
    "name": "Azur (Web Color)",
    "hex": "#F0FFFF"
  },
  {
    "name": "Azur Mist",
    "hex": "#F0FFFF"
  },
  {
    "name": "Azureish Weiß",
    "hex": "#DBE9F4"
  },
  {
    "name": "Baby Blau",
    "hex": "#89CFF0"
  },
  {
    "name": "Baby Blau Eyes",
    "hex": "#A1CAF1"
  },
  {
    "name": "Baby Rosa",
    "hex": "#F4C2C2"
  },
  {
    "name": "Baby Powder",
    "hex": "#FEFEFA"
  },
  {
    "name": "Baker-Miller Rosa",
    "hex": "#FF91AF"
  },
  {
    "name": "Ball Blau",
    "hex": "#21ABCD"
  },
  {
    "name": "Banana Mania",
    "hex": "#FAE7B5"
  },
  {
    "name": "Banana Gelb",
    "hex": "#FFE135"
  },
  {
    "name": "Bangladesh Grün",
    "hex": "#006A4E"
  },
  {
    "name": "Barbie Rosa",
    "hex": "#E0218A"
  },
  {
    "name": "Barn Rot",
    "hex": "#7C0A02"
  },
  {
    "name": "Battery Charged Blau",
    "hex": "#1DACD6"
  },
  {
    "name": "Battleship Grau",
    "hex": "#848482"
  },
  {
    "name": "Bazaar",
    "hex": "#98777B"
  },
  {
    "name": "Beau Blau",
    "hex": "#BCD4E6"
  },
  {
    "name": "Beaver",
    "hex": "#9F8170"
  },
  {
    "name": "Begonia",
    "hex": "#FA6E79"
  },
  {
    "name": "Beige",
    "hex": "#F5F5DC"
  },
  {
    "name": "B'dazzled Blau",
    "hex": "#2E5894"
  },
  {
    "name": "Big Dip O'ruby",
    "hex": "#9C2542"
  },
  {
    "name": "Big Foot Feet",
    "hex": "#E88E5A"
  },
  {
    "name": "Bisque",
    "hex": "#FFE4C4"
  },
  {
    "name": "Bistre",
    "hex": "#3D2B1F"
  },
  {
    "name": "Bistre Braun",
    "hex": "#967117"
  },
  {
    "name": "Bitter Lemon",
    "hex": "#CAE00D"
  },
  {
    "name": "Bitter Lime",
    "hex": "#BFFF00"
  },
  {
    "name": "Bittersweet",
    "hex": "#FE6F5E"
  },
  {
    "name": "Bittersweet Shimmer",
    "hex": "#BF4F51"
  },
  {
    "name": "Schwarz",
    "hex": "#000000"
  },
  {
    "name": "Schwarz Bean",
    "hex": "#3D0C02"
  },
  {
    "name": "Schwarz Coral",
    "hex": "#54626F"
  },
  {
    "name": "Schwarz Leather Jacket",
    "hex": "#253529"
  },
  {
    "name": "Schwarz Oliv",
    "hex": "#3B3C36"
  },
  {
    "name": "Schwarz Shadows",
    "hex": "#BFAFB2"
  },
  {
    "name": "Blanched Almond",
    "hex": "#FFEBCD"
  },
  {
    "name": "Blast-Off Bronze",
    "hex": "#A57164"
  },
  {
    "name": "Bleu De France",
    "hex": "#318CE7"
  },
  {
    "name": "Blizzard Blau",
    "hex": "#ACE5EE"
  },
  {
    "name": "Blond",
    "hex": "#FAF0BE"
  },
  {
    "name": "Blau",
    "hex": "#0000FF"
  },
  {
    "name": "Blau (Crayola)",
    "hex": "#1F75FE"
  },
  {
    "name": "Blau (Munsell)",
    "hex": "#0093AF"
  },
  {
    "name": "Blau (NCS)",
    "hex": "#0087BD"
  },
  {
    "name": "Blau (Pantone)",
    "hex": "#0018A8"
  },
  {
    "name": "Blau (Pigment)",
    "hex": "#333399"
  },
  {
    "name": "Blau (RYB)",
    "hex": "#0247FE"
  },
  {
    "name": "Blau Bell",
    "hex": "#A2A2D0"
  },
  {
    "name": "Blau Bolt",
    "hex": "#00B9FB"
  },
  {
    "name": "Blau-Grau",
    "hex": "#6699CC"
  },
  {
    "name": "Blau-Grün",
    "hex": "#0D98BA"
  },
  {
    "name": "Blau Jeans",
    "hex": "#5DADEC"
  },
  {
    "name": "Blau Lagoon",
    "hex": "#ACE5EE"
  },
  {
    "name": "Blau-Magenta Violett",
    "hex": "#553592"
  },
  {
    "name": "Blau Saphir",
    "hex": "#126180"
  },
  {
    "name": "Blau-Violett",
    "hex": "#8A2BE2"
  },
  {
    "name": "Blau Yonder",
    "hex": "#5072A7"
  },
  {
    "name": "Blueberry",
    "hex": "#4F86F7"
  },
  {
    "name": "Bluebonnet",
    "hex": "#1C1CF0"
  },
  {
    "name": "Blush",
    "hex": "#DE5D83"
  },
  {
    "name": "Bole",
    "hex": "#79443B"
  },
  {
    "name": "Bondi Blau",
    "hex": "#0095B6"
  },
  {
    "name": "Bone",
    "hex": "#E3DAC9"
  },
  {
    "name": "Booger Buster",
    "hex": "#DDE26A"
  },
  {
    "name": "Boston University Rot",
    "hex": "#CC0000"
  },
  {
    "name": "Bottle Grün",
    "hex": "#006A4E"
  },
  {
    "name": "Boysenberry",
    "hex": "#873260"
  },
  {
    "name": "Brandeis Blau",
    "hex": "#0070FF"
  },
  {
    "name": "Brass",
    "hex": "#B5A642"
  },
  {
    "name": "Brick Rot",
    "hex": "#CB4154"
  },
  {
    "name": "Leuchtend Cerulean",
    "hex": "#1DACD6"
  },
  {
    "name": "Leuchtend Grün",
    "hex": "#66FF00"
  },
  {
    "name": "Leuchtend Lavendel",
    "hex": "#BF94E4"
  },
  {
    "name": "Leuchtend Lilac",
    "hex": "#D891EF"
  },
  {
    "name": "Leuchtend Kastanienbraun",
    "hex": "#C32148"
  },
  {
    "name": "Leuchtend Navy Blau",
    "hex": "#1974D2"
  },
  {
    "name": "Leuchtend Rosa",
    "hex": "#FF007F"
  },
  {
    "name": "Leuchtend Türkis",
    "hex": "#08E8DE"
  },
  {
    "name": "Leuchtend Ube",
    "hex": "#D19FE8"
  },
  {
    "name": "Leuchtend Gelb (Crayola)",
    "hex": "#FFAA1D"
  },
  {
    "name": "Brilliant Azur",
    "hex": "#3399FF"
  },
  {
    "name": "Brilliant Lavendel",
    "hex": "#F4BBFF"
  },
  {
    "name": "Brilliant Rose",
    "hex": "#FF55A3"
  },
  {
    "name": "Brink Rosa",
    "hex": "#FB607F"
  },
  {
    "name": "British Racing Grün",
    "hex": "#004225"
  },
  {
    "name": "Bronze",
    "hex": "#CD7F32"
  },
  {
    "name": "Bronze Gelb",
    "hex": "#737000"
  },
  {
    "name": "Braun (Traditional)",
    "hex": "#964B00"
  },
  {
    "name": "Braun (Web)",
    "hex": "#A52A2A"
  },
  {
    "name": "Braun-Nose",
    "hex": "#6B4423"
  },
  {
    "name": "Braun Sugar",
    "hex": "#AF6E4D"
  },
  {
    "name": "Braun Gelb",
    "hex": "#cc9966"
  },
  {
    "name": "Brunswick Grün",
    "hex": "#1B4D3E"
  },
  {
    "name": "Bubble Gum",
    "hex": "#FFC1CC"
  },
  {
    "name": "Bubbles",
    "hex": "#E7FEFF"
  },
  {
    "name": "Bud Grün",
    "hex": "#7BB661"
  },
  {
    "name": "Buff",
    "hex": "#F0DC82"
  },
  {
    "name": "Bulgarian Rose",
    "hex": "#480607"
  },
  {
    "name": "Burgundy",
    "hex": "#800020"
  },
  {
    "name": "Burlywood",
    "hex": "#DEB887"
  },
  {
    "name": "Burnished Braun",
    "hex": "#A17A74"
  },
  {
    "name": "Burnt Orange",
    "hex": "#CC5500"
  },
  {
    "name": "Burnt Sienna",
    "hex": "#E97451"
  },
  {
    "name": "Burnt Umber",
    "hex": "#8A3324"
  },
  {
    "name": "Button Blau",
    "hex": "#24A0ED"
  },
  {
    "name": "Byzantine",
    "hex": "#BD33A4"
  },
  {
    "name": "Byzantium",
    "hex": "#702963"
  },
  {
    "name": "Cadet",
    "hex": "#536872"
  },
  {
    "name": "Cadet Blau",
    "hex": "#5F9EA0"
  },
  {
    "name": "Cadet Grau",
    "hex": "#91A3B0"
  },
  {
    "name": "Cadmium Grün",
    "hex": "#006B3C"
  },
  {
    "name": "Cadmium Orange",
    "hex": "#ED872D"
  },
  {
    "name": "Cadmium Rot",
    "hex": "#E30022"
  },
  {
    "name": "Cadmium Gelb",
    "hex": "#FFF600"
  },
  {
    "name": "Cafe Au Lait",
    "hex": "#A67B5B"
  },
  {
    "name": "Cafe Noir",
    "hex": "#4B3621"
  },
  {
    "name": "Cal Poly Pomona Grün",
    "hex": "#1E4D2B"
  },
  {
    "name": "Cambridge Blau",
    "hex": "#A3C1AD"
  },
  {
    "name": "Camel",
    "hex": "#C19A6B"
  },
  {
    "name": "Cameo Rosa",
    "hex": "#EFBBCC"
  },
  {
    "name": "Camouflage Grün",
    "hex": "#78866B"
  },
  {
    "name": "Canary",
    "hex": "#FFFF99"
  },
  {
    "name": "Canary Gelb",
    "hex": "#FFEF00"
  },
  {
    "name": "Candy Apple Rot",
    "hex": "#FF0800"
  },
  {
    "name": "Candy Rosa",
    "hex": "#E4717A"
  },
  {
    "name": "Capri",
    "hex": "#00BFFF"
  },
  {
    "name": "Caput Mortuum",
    "hex": "#592720"
  },
  {
    "name": "Cardinal",
    "hex": "#C41E3A"
  },
  {
    "name": "Caribbean Grün",
    "hex": "#00CC99"
  },
  {
    "name": "Carmine",
    "hex": "#960018"
  },
  {
    "name": "Carmine (M&P)",
    "hex": "#D70040"
  },
  {
    "name": "Carmine Rosa",
    "hex": "#EB4C42"
  },
  {
    "name": "Carmine Rot",
    "hex": "#FF0038"
  },
  {
    "name": "Carnation Rosa",
    "hex": "#FFA6C9"
  },
  {
    "name": "Carnelian",
    "hex": "#B31B1B"
  },
  {
    "name": "Carolina Blau",
    "hex": "#56A0D3"
  },
  {
    "name": "Carrot Orange",
    "hex": "#ED9121"
  },
  {
    "name": "Castleton Grün",
    "hex": "#00563F"
  },
  {
    "name": "Catalina Blau",
    "hex": "#062A78"
  },
  {
    "name": "Catawba",
    "hex": "#703642"
  },
  {
    "name": "Cedar Chest",
    "hex": "#C95A49"
  },
  {
    "name": "Ceil",
    "hex": "#92A1CF"
  },
  {
    "name": "Celadon",
    "hex": "#ACE1AF"
  },
  {
    "name": "Celadon Blau",
    "hex": "#007BA7"
  },
  {
    "name": "Celadon Grün",
    "hex": "#2F847C"
  },
  {
    "name": "Celeste",
    "hex": "#B2FFFF"
  },
  {
    "name": "Celestial Blau",
    "hex": "#4997D0"
  },
  {
    "name": "Cerise",
    "hex": "#DE3163"
  },
  {
    "name": "Cerise Rosa",
    "hex": "#EC3B83"
  },
  {
    "name": "Cerulean",
    "hex": "#007BA7"
  },
  {
    "name": "Cerulean Blau",
    "hex": "#2A52BE"
  },
  {
    "name": "Cerulean Frost",
    "hex": "#6D9BC3"
  },
  {
    "name": "CG Blau",
    "hex": "#007AA5"
  },
  {
    "name": "CG Rot",
    "hex": "#E03C31"
  },
  {
    "name": "Chamoisee",
    "hex": "#A0785A"
  },
  {
    "name": "Champagne",
    "hex": "#F7E7CE"
  },
  {
    "name": "Champagne Rosa",
    "hex": "#F1DDCF"
  },
  {
    "name": "Charcoal",
    "hex": "#36454F"
  },
  {
    "name": "Charleston Grün",
    "hex": "#232B2B"
  },
  {
    "name": "Charm Rosa",
    "hex": "#E68FAC"
  },
  {
    "name": "Chartreuse (Traditional)",
    "hex": "#DFFF00"
  },
  {
    "name": "Chartreuse (Web)",
    "hex": "#7FFF00"
  },
  {
    "name": "Cherry",
    "hex": "#DE3163"
  },
  {
    "name": "Cherry Blossom Rosa",
    "hex": "#FFB7C5"
  },
  {
    "name": "Chestnut",
    "hex": "#954535"
  },
  {
    "name": "China Rosa",
    "hex": "#DE6FA1"
  },
  {
    "name": "China Rose",
    "hex": "#A8516E"
  },
  {
    "name": "Chinese Rot",
    "hex": "#AA381E"
  },
  {
    "name": "Chinese Violett",
    "hex": "#856088"
  },
  {
    "name": "Chlorophyll Grün",
    "hex": "#4AFF00"
  },
  {
    "name": "Chocolate (Traditional)",
    "hex": "#7B3F00"
  },
  {
    "name": "Chocolate (Web)",
    "hex": "#D2691E"
  },
  {
    "name": "Chrome Gelb",
    "hex": "#FFA700"
  },
  {
    "name": "Cinereous",
    "hex": "#98817B"
  },
  {
    "name": "Cinnabar",
    "hex": "#E34234"
  },
  {
    "name": "Cinnamon",
    "hex": "#D2691E"
  },
  {
    "name": "Cinnamon Satin",
    "hex": "#CD607E"
  },
  {
    "name": "Citrine",
    "hex": "#E4D00A"
  },
  {
    "name": "Citron",
    "hex": "#9FA91F"
  },
  {
    "name": "Claret",
    "hex": "#7F1734"
  },
  {
    "name": "Classic Rose",
    "hex": "#FBCCE7"
  },
  {
    "name": "Cobalt Blau",
    "hex": "#0047AB"
  },
  {
    "name": "Cocoa Braun",
    "hex": "#D2691E"
  },
  {
    "name": "Coconut",
    "hex": "#965A3E"
  },
  {
    "name": "Coffee",
    "hex": "#6F4E37"
  },
  {
    "name": "Columbia Blau",
    "hex": "#C4D8E2"
  },
  {
    "name": "Congo Rosa",
    "hex": "#F88379"
  },
  {
    "name": "Cool Schwarz",
    "hex": "#002E63"
  },
  {
    "name": "Cool Grau",
    "hex": "#8C92AC"
  },
  {
    "name": "Kupfer",
    "hex": "#B87333"
  },
  {
    "name": "Kupfer (Crayola)",
    "hex": "#DA8A67"
  },
  {
    "name": "Kupfer Penny",
    "hex": "#AD6F69"
  },
  {
    "name": "Kupfer Rot",
    "hex": "#CB6D51"
  },
  {
    "name": "Kupfer Rose",
    "hex": "#996666"
  },
  {
    "name": "Coquelicot",
    "hex": "#FF3800"
  },
  {
    "name": "Coral",
    "hex": "#FF7F50"
  },
  {
    "name": "Coral Rosa",
    "hex": "#F88379"
  },
  {
    "name": "Coral Rot",
    "hex": "#FF4040"
  },
  {
    "name": "Coral Reef",
    "hex": "#FD7C6E"
  },
  {
    "name": "Cordovan",
    "hex": "#893F45"
  },
  {
    "name": "Corn",
    "hex": "#FBEC5D"
  },
  {
    "name": "Cornell Rot",
    "hex": "#B31B1B"
  },
  {
    "name": "Cornflower Blau",
    "hex": "#6495ED"
  },
  {
    "name": "Cornsilk",
    "hex": "#FFF8DC"
  },
  {
    "name": "Cosmic Cobalt",
    "hex": "#2E2D88"
  },
  {
    "name": "Cosmic Latte",
    "hex": "#FFF8E7"
  },
  {
    "name": "Coyote Braun",
    "hex": "#81613C"
  },
  {
    "name": "Cotton Candy",
    "hex": "#FFBCD9"
  },
  {
    "name": "Cream",
    "hex": "#FFFDD0"
  },
  {
    "name": "Karmesin",
    "hex": "#DC143C"
  },
  {
    "name": "Karmesin Glory",
    "hex": "#BE0032"
  },
  {
    "name": "Karmesin Rot",
    "hex": "#990000"
  },
  {
    "name": "Cultured",
    "hex": "#F5F5F5"
  },
  {
    "name": "Cyan",
    "hex": "#00FFFF"
  },
  {
    "name": "Cyan Azur",
    "hex": "#4E82B4"
  },
  {
    "name": "Cyan-Blau Azur",
    "hex": "#4682BF"
  },
  {
    "name": "Cyan Cobalt Blau",
    "hex": "#28589C"
  },
  {
    "name": "Cyan Cornflower Blau",
    "hex": "#188BC2"
  },
  {
    "name": "Cyan (Process)",
    "hex": "#00B7EB"
  },
  {
    "name": "Cyber Grape",
    "hex": "#58427C"
  },
  {
    "name": "Cyber Gelb",
    "hex": "#FFD300"
  },
  {
    "name": "Cyclamen",
    "hex": "#F56FA1"
  },
  {
    "name": "Daffodil",
    "hex": "#FFFF31"
  },
  {
    "name": "Dandelion",
    "hex": "#F0E130"
  },
  {
    "name": "Dunkel Blau",
    "hex": "#00008B"
  },
  {
    "name": "Dunkel Blau-Grau",
    "hex": "#666699"
  },
  {
    "name": "Dunkel Braun",
    "hex": "#654321"
  },
  {
    "name": "Dunkel Braun-Tangelo",
    "hex": "#88654E"
  },
  {
    "name": "Dunkel Byzantium",
    "hex": "#5D3954"
  },
  {
    "name": "Dunkel Candy Apple Rot",
    "hex": "#A40000"
  },
  {
    "name": "Dunkel Cerulean",
    "hex": "#08457E"
  },
  {
    "name": "Dunkel Chestnut",
    "hex": "#986960"
  },
  {
    "name": "Dunkel Coral",
    "hex": "#CD5B45"
  },
  {
    "name": "Dunkel Cyan",
    "hex": "#008B8B"
  },
  {
    "name": "Dunkel Electric Blau",
    "hex": "#536878"
  },
  {
    "name": "Dunkel Goldenrod",
    "hex": "#B8860B"
  },
  {
    "name": "Dunkel Grau (X11)",
    "hex": "#A9A9A9"
  },
  {
    "name": "Dunkel Grün",
    "hex": "#013220"
  },
  {
    "name": "Dunkel Grün (X11)",
    "hex": "#006400"
  },
  {
    "name": "Dunkel Gunmetal",
    "hex": "#1F262A"
  },
  {
    "name": "Dunkel Imperial Blau",
    "hex": "#00416A"
  },
  {
    "name": "Dunkel Imperial Blau",
    "hex": "#00147E"
  },
  {
    "name": "Dunkel Jungle Grün",
    "hex": "#1A2421"
  },
  {
    "name": "Dunkel Khaki",
    "hex": "#BDB76B"
  },
  {
    "name": "Dunkel Lava",
    "hex": "#483C32"
  },
  {
    "name": "Dunkel Lavendel",
    "hex": "#734F96"
  },
  {
    "name": "Dunkel Liver",
    "hex": "#534B4F"
  },
  {
    "name": "Dunkel Liver (Horses)",
    "hex": "#543D37"
  },
  {
    "name": "Dunkel Magenta",
    "hex": "#8B008B"
  },
  {
    "name": "Dunkel Medium Grau",
    "hex": "#A9A9A9"
  },
  {
    "name": "Dunkel Midnight Blau",
    "hex": "#003366"
  },
  {
    "name": "Dunkel Moss Grün",
    "hex": "#4A5D23"
  },
  {
    "name": "Dunkel Oliv Grün",
    "hex": "#556B2F"
  },
  {
    "name": "Dunkel Orange",
    "hex": "#FF8C00"
  },
  {
    "name": "Dunkel Orchid",
    "hex": "#9932CC"
  },
  {
    "name": "Dunkel Pastel Blau",
    "hex": "#779ECB"
  },
  {
    "name": "Dunkel Pastel Grün",
    "hex": "#03C03C"
  },
  {
    "name": "Dunkel Pastel Lila",
    "hex": "#966FD6"
  },
  {
    "name": "Dunkel Pastel Rot",
    "hex": "#C23B22"
  },
  {
    "name": "Dunkel Rosa",
    "hex": "#E75480"
  },
  {
    "name": "Dunkel Powder Blau",
    "hex": "#003399"
  },
  {
    "name": "Dunkel Puce",
    "hex": "#4F3A3C"
  },
  {
    "name": "Dunkel Lila",
    "hex": "#301934"
  },
  {
    "name": "Dunkel Raspberry",
    "hex": "#872657"
  },
  {
    "name": "Dunkel Rot",
    "hex": "#8B0000"
  },
  {
    "name": "Dunkel Salmon",
    "hex": "#E9967A"
  },
  {
    "name": "Dunkel Scharlach",
    "hex": "#560319"
  },
  {
    "name": "Dunkel Sea Grün",
    "hex": "#8FBC8F"
  },
  {
    "name": "Dunkel Sienna",
    "hex": "#3C1414"
  },
  {
    "name": "Dunkel Sky Blau",
    "hex": "#8CBED6"
  },
  {
    "name": "Dunkel Slate Blau",
    "hex": "#483D8B"
  },
  {
    "name": "Dunkel Slate Grau",
    "hex": "#2F4F4F"
  },
  {
    "name": "Dunkel Spring Grün",
    "hex": "#177245"
  },
  {
    "name": "Dunkel Tan",
    "hex": "#918151"
  },
  {
    "name": "Dunkel Tangerine",
    "hex": "#FFA812"
  },
  {
    "name": "Dunkel Taupe",
    "hex": "#483C32"
  },
  {
    "name": "Dunkel Terra Cotta",
    "hex": "#CC4E5C"
  },
  {
    "name": "Dunkel Türkis",
    "hex": "#00CED1"
  },
  {
    "name": "Dunkel Vanilla",
    "hex": "#D1BEA8"
  },
  {
    "name": "Dunkel Violett",
    "hex": "#9400D3"
  },
  {
    "name": "Dunkel Gelb",
    "hex": "#9B870C"
  },
  {
    "name": "Dartmouth Grün",
    "hex": "#00703C"
  },
  {
    "name": "Davy's Grau",
    "hex": "#555555"
  },
  {
    "name": "Debian Rot",
    "hex": "#D70A53"
  },
  {
    "name": "Tief Aquamarine",
    "hex": "#40826D"
  },
  {
    "name": "Tief Carmine",
    "hex": "#A9203E"
  },
  {
    "name": "Tief Carmine Rosa",
    "hex": "#EF3038"
  },
  {
    "name": "Tief Carrot Orange",
    "hex": "#E9692C"
  },
  {
    "name": "Tief Cerise",
    "hex": "#DA3287"
  },
  {
    "name": "Tief Champagne",
    "hex": "#FAD6A5"
  },
  {
    "name": "Tief Chestnut",
    "hex": "#B94E48"
  },
  {
    "name": "Tief Coffee",
    "hex": "#704241"
  },
  {
    "name": "Tief Fuchsia",
    "hex": "#C154C1"
  },
  {
    "name": "Tief Grün",
    "hex": "#056608"
  },
  {
    "name": "Tief Grün-Cyan Türkis",
    "hex": "#0E7C61"
  },
  {
    "name": "Tief Jungle Grün",
    "hex": "#004B49"
  },
  {
    "name": "Tief Koamaru",
    "hex": "#333366"
  },
  {
    "name": "Tief Lemon",
    "hex": "#F5C71A"
  },
  {
    "name": "Tief Lilac",
    "hex": "#9955BB"
  },
  {
    "name": "Tief Magenta",
    "hex": "#CC00CC"
  },
  {
    "name": "Tief Kastanienbraun",
    "hex": "#820000"
  },
  {
    "name": "Tief Mauve",
    "hex": "#D473D4"
  },
  {
    "name": "Tief Moss Grün",
    "hex": "#355E3B"
  },
  {
    "name": "Tief Peach",
    "hex": "#FFCBA4"
  },
  {
    "name": "Tief Rosa",
    "hex": "#FF1493"
  },
  {
    "name": "Tief Puce",
    "hex": "#A95C68"
  },
  {
    "name": "Tief Rot",
    "hex": "#850101"
  },
  {
    "name": "Tief Rubin",
    "hex": "#843F5B"
  },
  {
    "name": "Tief Saffron",
    "hex": "#FF9933"
  },
  {
    "name": "Tief Sky Blau",
    "hex": "#00BFFF"
  },
  {
    "name": "Tief Space Sparkle",
    "hex": "#4A646C"
  },
  {
    "name": "Tief Spring Bud",
    "hex": "#556B2F"
  },
  {
    "name": "Tief Taupe",
    "hex": "#7E5E60"
  },
  {
    "name": "Tief Tuscan Rot",
    "hex": "#66424D"
  },
  {
    "name": "Tief Violett",
    "hex": "#330066"
  },
  {
    "name": "Deer",
    "hex": "#BA8759"
  },
  {
    "name": "Denim",
    "hex": "#1560BD"
  },
  {
    "name": "Denim Blau",
    "hex": "#2243B6"
  },
  {
    "name": "Desaturated Cyan",
    "hex": "#669999"
  },
  {
    "name": "Desert",
    "hex": "#C19A6B"
  },
  {
    "name": "Desert Sand",
    "hex": "#EDC9AF"
  },
  {
    "name": "Desire",
    "hex": "#EA3C53"
  },
  {
    "name": "Diamond",
    "hex": "#B9F2FF"
  },
  {
    "name": "Dim Grau",
    "hex": "#696969"
  },
  {
    "name": "Dingy Dungeon",
    "hex": "#C53151"
  },
  {
    "name": "Dirt",
    "hex": "#9B7653"
  },
  {
    "name": "Dodger Blau",
    "hex": "#1E90FF"
  },
  {
    "name": "Dodie Gelb",
    "hex": "#FEF65B"
  },
  {
    "name": "Dogwood Rose",
    "hex": "#D71868"
  },
  {
    "name": "Dollar Bill",
    "hex": "#85BB65"
  },
  {
    "name": "Dolphin Grau",
    "hex": "#828E84"
  },
  {
    "name": "Donkey Braun",
    "hex": "#664C28"
  },
  {
    "name": "Drab",
    "hex": "#967117"
  },
  {
    "name": "Duke Blau",
    "hex": "#00009C"
  },
  {
    "name": "Dust Storm",
    "hex": "#E5CCC9"
  },
  {
    "name": "Dutch Weiß",
    "hex": "#EFDFBB"
  },
  {
    "name": "Earth Gelb",
    "hex": "#E1A95F"
  },
  {
    "name": "Ebony",
    "hex": "#555D50"
  },
  {
    "name": "Ecru",
    "hex": "#C2B280"
  },
  {
    "name": "Eerie Schwarz",
    "hex": "#1B1B1B"
  },
  {
    "name": "Eggplant",
    "hex": "#614051"
  },
  {
    "name": "Eggshell",
    "hex": "#F0EAD6"
  },
  {
    "name": "Egyptian Blau",
    "hex": "#1034A6"
  },
  {
    "name": "Electric Blau",
    "hex": "#7DF9FF"
  },
  {
    "name": "Electric Karmesin",
    "hex": "#FF003F"
  },
  {
    "name": "Electric Cyan",
    "hex": "#00FFFF"
  },
  {
    "name": "Electric Grün",
    "hex": "#00FF00"
  },
  {
    "name": "Electric Indigo",
    "hex": "#6F00FF"
  },
  {
    "name": "Electric Lavendel",
    "hex": "#F4BBFF"
  },
  {
    "name": "Electric Lime",
    "hex": "#CCFF00"
  },
  {
    "name": "Electric Lila",
    "hex": "#BF00FF"
  },
  {
    "name": "Electric Ultramarine",
    "hex": "#3F00FF"
  },
  {
    "name": "Electric Violett",
    "hex": "#8F00FF"
  },
  {
    "name": "Electric Gelb",
    "hex": "#FFFF33"
  },
  {
    "name": "Smaragd",
    "hex": "#50C878"
  },
  {
    "name": "Eminence",
    "hex": "#6C3082"
  },
  {
    "name": "English Grün",
    "hex": "#1B4D3E"
  },
  {
    "name": "English Lavendel",
    "hex": "#B48395"
  },
  {
    "name": "English Rot",
    "hex": "#AB4B52"
  },
  {
    "name": "English Vermillion",
    "hex": "#CC474B"
  },
  {
    "name": "English Violett",
    "hex": "#563C5C"
  },
  {
    "name": "Eton Blau",
    "hex": "#96C8A2"
  },
  {
    "name": "Eucalyptus",
    "hex": "#44D7A8"
  },
  {
    "name": "Fallow",
    "hex": "#C19A6B"
  },
  {
    "name": "Falu Rot",
    "hex": "#801818"
  },
  {
    "name": "Fandango",
    "hex": "#B53389"
  },
  {
    "name": "Fandango Rosa",
    "hex": "#DE5285"
  },
  {
    "name": "Fashion Fuchsia",
    "hex": "#F400A1"
  },
  {
    "name": "Fawn",
    "hex": "#E5AA70"
  },
  {
    "name": "Feldgrau",
    "hex": "#4D5D53"
  },
  {
    "name": "Feldspar",
    "hex": "#FDD5B1"
  },
  {
    "name": "Fern Grün",
    "hex": "#4F7942"
  },
  {
    "name": "Ferrari Rot",
    "hex": "#FF2800"
  },
  {
    "name": "Field Drab",
    "hex": "#6C541E"
  },
  {
    "name": "Fiery Rose",
    "hex": "#FF5470"
  },
  {
    "name": "Firebrick",
    "hex": "#B22222"
  },
  {
    "name": "Fire Engine Rot",
    "hex": "#CE2029"
  },
  {
    "name": "Flame",
    "hex": "#E25822"
  },
  {
    "name": "Flamingo Rosa",
    "hex": "#FC8EAC"
  },
  {
    "name": "Flattery",
    "hex": "#6B4423"
  },
  {
    "name": "Flavescent",
    "hex": "#F7E98E"
  },
  {
    "name": "Flax",
    "hex": "#EEDC82"
  },
  {
    "name": "Flirt",
    "hex": "#A2006D"
  },
  {
    "name": "Floral Weiß",
    "hex": "#FFFAF0"
  },
  {
    "name": "Fluorescent Orange",
    "hex": "#FFBF00"
  },
  {
    "name": "Fluorescent Rosa",
    "hex": "#FF1493"
  },
  {
    "name": "Fluorescent Gelb",
    "hex": "#CCFF00"
  },
  {
    "name": "Folly",
    "hex": "#FF004F"
  },
  {
    "name": "Forest Grün (Traditional)",
    "hex": "#014421"
  },
  {
    "name": "Forest Grün (Web)",
    "hex": "#228B22"
  },
  {
    "name": "French Beige",
    "hex": "#A67B5B"
  },
  {
    "name": "French Bistre",
    "hex": "#856D4D"
  },
  {
    "name": "French Blau",
    "hex": "#0072BB"
  },
  {
    "name": "French Fuchsia",
    "hex": "#FD3F92"
  },
  {
    "name": "French Lilac",
    "hex": "#86608E"
  },
  {
    "name": "French Lime",
    "hex": "#9EFD38"
  },
  {
    "name": "French Mauve",
    "hex": "#D473D4"
  },
  {
    "name": "French Rosa",
    "hex": "#FD6C9E"
  },
  {
    "name": "French Plum",
    "hex": "#811453"
  },
  {
    "name": "French Puce",
    "hex": "#4E1609"
  },
  {
    "name": "French Raspberry",
    "hex": "#C72C48"
  },
  {
    "name": "French Rose",
    "hex": "#F64A8A"
  },
  {
    "name": "French Sky Blau",
    "hex": "#77B5FE"
  },
  {
    "name": "French Violett",
    "hex": "#8806CE"
  },
  {
    "name": "French Wine",
    "hex": "#AC1E44"
  },
  {
    "name": "Fresh Air",
    "hex": "#A6E7FF"
  },
  {
    "name": "Frogert",
    "hex": "#E936A7"
  },
  {
    "name": "Fuchsia",
    "hex": "#FF00FF"
  },
  {
    "name": "Fuchsia (Crayola)",
    "hex": "#C154C1"
  },
  {
    "name": "Fuchsia Rosa",
    "hex": "#FF77FF"
  },
  {
    "name": "Fuchsia Lila",
    "hex": "#CC397B"
  },
  {
    "name": "Fuchsia Rose",
    "hex": "#C74375"
  },
  {
    "name": "Fulvous",
    "hex": "#E48400"
  },
  {
    "name": "Fuzzy Wuzzy",
    "hex": "#CC6666"
  },
  {
    "name": "Gainsboro",
    "hex": "#DCDCDC"
  },
  {
    "name": "Gamboge",
    "hex": "#E49B0F"
  },
  {
    "name": "Gamboge Orange (Braun)",
    "hex": "#996600"
  },
  {
    "name": "Gargoyle Gas",
    "hex": "#FFDF46"
  },
  {
    "name": "Generic Viridian",
    "hex": "#007F66"
  },
  {
    "name": "Ghost Weiß",
    "hex": "#F8F8FF"
  },
  {
    "name": "Giant's Club",
    "hex": "#B05C52"
  },
  {
    "name": "Giants Orange",
    "hex": "#FE5A1D"
  },
  {
    "name": "Ginger",
    "hex": "#B06500"
  },
  {
    "name": "Glaucous",
    "hex": "#6082B6"
  },
  {
    "name": "Glitter",
    "hex": "#E6E8FA"
  },
  {
    "name": "Glossy Grape",
    "hex": "#AB92B3"
  },
  {
    "name": "GO Grün",
    "hex": "#00AB66"
  },
  {
    "name": "Gold (Metallic)",
    "hex": "#D4AF37"
  },
  {
    "name": "Gold (Web) (Golden)",
    "hex": "#FFD700"
  },
  {
    "name": "Gold Fusion",
    "hex": "#85754E"
  },
  {
    "name": "Golden Braun",
    "hex": "#996515"
  },
  {
    "name": "Golden Poppy",
    "hex": "#FCC200"
  },
  {
    "name": "Golden Gelb",
    "hex": "#FFDF00"
  },
  {
    "name": "Goldenrod",
    "hex": "#DAA520"
  },
  {
    "name": "Granite Grau",
    "hex": "#676767"
  },
  {
    "name": "Granny Smith Apple",
    "hex": "#A8E4A0"
  },
  {
    "name": "Grape",
    "hex": "#6F2DA8"
  },
  {
    "name": "Grau",
    "hex": "#808080"
  },
  {
    "name": "Grau (HTML/CSS Grau)",
    "hex": "#808080"
  },
  {
    "name": "Grau (X11 Grau)",
    "hex": "#BEBEBE"
  },
  {
    "name": "Grau-Asparagus",
    "hex": "#465945"
  },
  {
    "name": "Grau-Blau",
    "hex": "#8C92AC"
  },
  {
    "name": "Grün (Color Wheel) (X11 Grün)",
    "hex": "#00FF00"
  },
  {
    "name": "Grün (Crayola)",
    "hex": "#1CAC78"
  },
  {
    "name": "Grün (HTML/CSS Color)",
    "hex": "#008000"
  },
  {
    "name": "Grün (Munsell)",
    "hex": "#00A877"
  },
  {
    "name": "Grün (NCS)",
    "hex": "#009F6B"
  },
  {
    "name": "Grün (Pantone)",
    "hex": "#00AD43"
  },
  {
    "name": "Grün (Pigment)",
    "hex": "#00A550"
  },
  {
    "name": "Grün (RYB)",
    "hex": "#66B032"
  },
  {
    "name": "Grün-Blau",
    "hex": "#1164B4"
  },
  {
    "name": "Grün-Cyan",
    "hex": "#009966"
  },
  {
    "name": "Grün Lizard",
    "hex": "#A7F432"
  },
  {
    "name": "Grün Sheen",
    "hex": "#6EAEA1"
  },
  {
    "name": "Grün-Gelb",
    "hex": "#ADFF2F"
  },
  {
    "name": "Grizzly",
    "hex": "#885818"
  },
  {
    "name": "Grullo",
    "hex": "#A99A86"
  },
  {
    "name": "Guppie Grün",
    "hex": "#00FF7F"
  },
  {
    "name": "Gunmetal",
    "hex": "#2a3439"
  },
  {
    "name": "Halaya Ube",
    "hex": "#663854"
  },
  {
    "name": "Han Blau",
    "hex": "#446CCF"
  },
  {
    "name": "Han Lila",
    "hex": "#5218FA"
  },
  {
    "name": "Hansa Gelb",
    "hex": "#E9D66B"
  },
  {
    "name": "Harlequin",
    "hex": "#3FFF00"
  },
  {
    "name": "Harlequin Grün",
    "hex": "#46CB18"
  },
  {
    "name": "Harvard Karmesin",
    "hex": "#C90016"
  },
  {
    "name": "Harvest Gold",
    "hex": "#DA9100"
  },
  {
    "name": "Heart Gold",
    "hex": "#808000"
  },
  {
    "name": "Heat Wave",
    "hex": "#FF7A00"
  },
  {
    "name": "Heidelberg Rot",
    "hex": "#960018"
  },
  {
    "name": "Heliotrope",
    "hex": "#DF73FF"
  },
  {
    "name": "Heliotrope Grau",
    "hex": "#AA98A9"
  },
  {
    "name": "Heliotrope Magenta",
    "hex": "#AA00BB"
  },
  {
    "name": "Hollywood Cerise",
    "hex": "#F400A1"
  },
  {
    "name": "Honeydew",
    "hex": "#F0FFF0"
  },
  {
    "name": "Honolulu Blau",
    "hex": "#006DB0"
  },
  {
    "name": "Hooker's Grün",
    "hex": "#49796B"
  },
  {
    "name": "Hot Magenta",
    "hex": "#FF1DCE"
  },
  {
    "name": "Hot Rosa",
    "hex": "#FF69B4"
  },
  {
    "name": "Hunter Grün",
    "hex": "#355E3B"
  },
  {
    "name": "Iceberg",
    "hex": "#71A6D2"
  },
  {
    "name": "Icterine",
    "hex": "#FCF75E"
  },
  {
    "name": "Iguana Grün",
    "hex": "#71BC78"
  },
  {
    "name": "Illuminating Smaragd",
    "hex": "#319177"
  },
  {
    "name": "Imperial",
    "hex": "#602F6B"
  },
  {
    "name": "Imperial Blau",
    "hex": "#002395"
  },
  {
    "name": "Imperial Lila",
    "hex": "#66023C"
  },
  {
    "name": "Imperial Rot",
    "hex": "#ED2939"
  },
  {
    "name": "Inchworm",
    "hex": "#B2EC5D"
  },
  {
    "name": "Independence",
    "hex": "#4C516D"
  },
  {
    "name": "India Grün",
    "hex": "#138808"
  },
  {
    "name": "Indian Rot",
    "hex": "#CD5C5C"
  },
  {
    "name": "Indian Gelb",
    "hex": "#E3A857"
  },
  {
    "name": "Indigo",
    "hex": "#4B0082"
  },
  {
    "name": "Indigo Dye",
    "hex": "#091F92"
  },
  {
    "name": "Indigo (Web)",
    "hex": "#4B0082"
  },
  {
    "name": "Infra Rot",
    "hex": "#FF496C"
  },
  {
    "name": "Interdimensional Blau",
    "hex": "#360CCC"
  },
  {
    "name": "International Klein Blau",
    "hex": "#002FA7"
  },
  {
    "name": "International Orange (Aerospace)",
    "hex": "#FF4F00"
  },
  {
    "name": "International Orange (Engineering)",
    "hex": "#BA160C"
  },
  {
    "name": "International Orange (Golden Gate Bridge)",
    "hex": "#C0362C"
  },
  {
    "name": "Iris",
    "hex": "#5A4FCF"
  },
  {
    "name": "Irresistible",
    "hex": "#B3446C"
  },
  {
    "name": "Isabelline",
    "hex": "#F4F0EC"
  },
  {
    "name": "Islamic Grün",
    "hex": "#009000"
  },
  {
    "name": "Italian Sky Blau",
    "hex": "#B2FFFF"
  },
  {
    "name": "Ivory",
    "hex": "#FFFFF0"
  },
  {
    "name": "Jade",
    "hex": "#00A86B"
  },
  {
    "name": "Japanese Carmine",
    "hex": "#9D2933"
  },
  {
    "name": "Japanese Indigo",
    "hex": "#264348"
  },
  {
    "name": "Japanese Violett",
    "hex": "#5B3256"
  },
  {
    "name": "Jasmine",
    "hex": "#F8DE7E"
  },
  {
    "name": "Jasper",
    "hex": "#D73B3E"
  },
  {
    "name": "Jazzberry Jam",
    "hex": "#A50B5E"
  },
  {
    "name": "Jelly Bean",
    "hex": "#DA614E"
  },
  {
    "name": "Jet",
    "hex": "#343434"
  },
  {
    "name": "Jonquil",
    "hex": "#F4CA16"
  },
  {
    "name": "Jordy Blau",
    "hex": "#8AB9F1"
  },
  {
    "name": "June Bud",
    "hex": "#BDDA57"
  },
  {
    "name": "Jungle Grün",
    "hex": "#29AB87"
  },
  {
    "name": "Kelly Grün",
    "hex": "#4CBB17"
  },
  {
    "name": "Kenyan Kupfer",
    "hex": "#7C1C05"
  },
  {
    "name": "Keppel",
    "hex": "#3AB09E"
  },
  {
    "name": "Key Lime",
    "hex": "#E8F48C"
  },
  {
    "name": "Khaki (HTML/CSS) (Khaki)",
    "hex": "#C3B091"
  },
  {
    "name": "Khaki (X11) (Hell Khaki)",
    "hex": "#F0E68C"
  },
  {
    "name": "Kiwi",
    "hex": "#8EE53F"
  },
  {
    "name": "Kobe",
    "hex": "#882D17"
  },
  {
    "name": "Kobi",
    "hex": "#E79FC4"
  },
  {
    "name": "Kobicha",
    "hex": "#6B4423"
  },
  {
    "name": "Kombu Grün",
    "hex": "#354230"
  },
  {
    "name": "KSU Lila",
    "hex": "#512888"
  },
  {
    "name": "KU Karmesin",
    "hex": "#E8000D"
  },
  {
    "name": "La Salle Grün",
    "hex": "#087830"
  },
  {
    "name": "Languid Lavendel",
    "hex": "#D6CADD"
  },
  {
    "name": "Lapis Lazuli",
    "hex": "#26619C"
  },
  {
    "name": "Laser Lemon",
    "hex": "#FFFF66"
  },
  {
    "name": "Laurel Grün",
    "hex": "#A9BA9D"
  },
  {
    "name": "Lava",
    "hex": "#CF1020"
  },
  {
    "name": "Lavendel (Floral)",
    "hex": "#B57EDC"
  },
  {
    "name": "Lavendel (Web)",
    "hex": "#E6E6FA"
  },
  {
    "name": "Lavendel Blau",
    "hex": "#CCCCFF"
  },
  {
    "name": "Lavendel Blush",
    "hex": "#FFF0F5"
  },
  {
    "name": "Lavendel Grau",
    "hex": "#C4C3D0"
  },
  {
    "name": "Lavendel Indigo",
    "hex": "#9457EB"
  },
  {
    "name": "Lavendel Magenta",
    "hex": "#EE82EE"
  },
  {
    "name": "Lavendel Mist",
    "hex": "#E6E6FA"
  },
  {
    "name": "Lavendel Rosa",
    "hex": "#FBAED2"
  },
  {
    "name": "Lavendel Lila",
    "hex": "#967BB6"
  },
  {
    "name": "Lavendel Rose",
    "hex": "#FBA0E3"
  },
  {
    "name": "Lawn Grün",
    "hex": "#7CFC00"
  },
  {
    "name": "Lemon",
    "hex": "#FFF700"
  },
  {
    "name": "Lemon Chiffon",
    "hex": "#FFFACD"
  },
  {
    "name": "Lemon Curry",
    "hex": "#CCA01D"
  },
  {
    "name": "Lemon Glacier",
    "hex": "#FDFF00"
  },
  {
    "name": "Lemon Lime",
    "hex": "#E3FF00"
  },
  {
    "name": "Lemon Meringue",
    "hex": "#F6EABE"
  },
  {
    "name": "Lemon Gelb",
    "hex": "#FFF44F"
  },
  {
    "name": "Licorice",
    "hex": "#1A1110"
  },
  {
    "name": "Liberty",
    "hex": "#545AA7"
  },
  {
    "name": "Hell Apricot",
    "hex": "#FDD5B1"
  },
  {
    "name": "Hell Blau",
    "hex": "#ADD8E6"
  },
  {
    "name": "Hell Braun",
    "hex": "#B5651D"
  },
  {
    "name": "Hell Carmine Rosa",
    "hex": "#E66771"
  },
  {
    "name": "Hell Cobalt Blau",
    "hex": "#88ACE0"
  },
  {
    "name": "Hell Coral",
    "hex": "#F08080"
  },
  {
    "name": "Hell Cornflower Blau",
    "hex": "#93CCEA"
  },
  {
    "name": "Hell Karmesin",
    "hex": "#F56991"
  },
  {
    "name": "Hell Cyan",
    "hex": "#E0FFFF"
  },
  {
    "name": "Hell Tief Rosa",
    "hex": "#FF5CCD"
  },
  {
    "name": "Hell French Beige",
    "hex": "#C8AD7F"
  },
  {
    "name": "Hell Fuchsia Rosa",
    "hex": "#F984EF"
  },
  {
    "name": "Hell Goldenrod Gelb",
    "hex": "#FAFAD2"
  },
  {
    "name": "Hell Grau",
    "hex": "#D3D3D3"
  },
  {
    "name": "Hell Grayish Magenta",
    "hex": "#CC99CC"
  },
  {
    "name": "Hell Grün",
    "hex": "#90EE90"
  },
  {
    "name": "Hell Hot Rosa",
    "hex": "#FFB3DE"
  },
  {
    "name": "Hell Khaki",
    "hex": "#F0E68C"
  },
  {
    "name": "Hell Medium Orchid",
    "hex": "#D39BCB"
  },
  {
    "name": "Hell Moss Grün",
    "hex": "#ADDFAD"
  },
  {
    "name": "Hell Orange",
    "hex": "#FED8B1"
  },
  {
    "name": "Hell Orchid",
    "hex": "#E6A8D7"
  },
  {
    "name": "Hell Pastel Lila",
    "hex": "#B19CD9"
  },
  {
    "name": "Hell Rosa",
    "hex": "#FFB6C1"
  },
  {
    "name": "Hell Rot Ochre",
    "hex": "#E97451"
  },
  {
    "name": "Hell Salmon",
    "hex": "#FFA07A"
  },
  {
    "name": "Hell Salmon Rosa",
    "hex": "#FF9999"
  },
  {
    "name": "Hell Sea Grün",
    "hex": "#20B2AA"
  },
  {
    "name": "Hell Sky Blau",
    "hex": "#87CEFA"
  },
  {
    "name": "Hell Slate Grau",
    "hex": "#778899"
  },
  {
    "name": "Hell Steel Blau",
    "hex": "#B0C4DE"
  },
  {
    "name": "Hell Taupe",
    "hex": "#B38B6D"
  },
  {
    "name": "Hell Thulian Rosa",
    "hex": "#E68FAC"
  },
  {
    "name": "Hell Gelb",
    "hex": "#FFFFE0"
  },
  {
    "name": "Lilac",
    "hex": "#C8A2C8"
  },
  {
    "name": "Lilac Luster",
    "hex": "#AE98AA"
  },
  {
    "name": "Lime (Color Wheel)",
    "hex": "#BFFF00"
  },
  {
    "name": "Lime (Web) (X11 Grün)",
    "hex": "#00FF00"
  },
  {
    "name": "Lime Grün",
    "hex": "#32CD32"
  },
  {
    "name": "Limerick",
    "hex": "#9DC209"
  },
  {
    "name": "Lincoln Grün",
    "hex": "#195905"
  },
  {
    "name": "Linen",
    "hex": "#FAF0E6"
  },
  {
    "name": "Loeen (Lopen) Look",
    "hex": "#15F2FD"
  },
  {
    "name": "Liseran Lila",
    "hex": "#DE6FA1"
  },
  {
    "name": "Little Boy Blau",
    "hex": "#6CA0DC"
  },
  {
    "name": "Liver",
    "hex": "#674C47"
  },
  {
    "name": "Liver (Dogs)",
    "hex": "#B86D29"
  },
  {
    "name": "Liver (Organ)",
    "hex": "#6C2E1F"
  },
  {
    "name": "Liver Chestnut",
    "hex": "#987456"
  },
  {
    "name": "Livid",
    "hex": "#6699CC"
  },
  {
    "name": "Lumber",
    "hex": "#FFE4CD"
  },
  {
    "name": "Lust",
    "hex": "#E62020"
  },
  {
    "name": "Maastricht Blau",
    "hex": "#001C3D"
  },
  {
    "name": "Macaroni And Cheese",
    "hex": "#FFBD88"
  },
  {
    "name": "Madder Lake",
    "hex": "#CC3336"
  },
  {
    "name": "Magenta",
    "hex": "#FF00FF"
  },
  {
    "name": "Magenta (Crayola)",
    "hex": "#FF55A3"
  },
  {
    "name": "Magenta (Dye)",
    "hex": "#CA1F7B"
  },
  {
    "name": "Magenta (Pantone)",
    "hex": "#D0417E"
  },
  {
    "name": "Magenta (Process)",
    "hex": "#FF0090"
  },
  {
    "name": "Magenta Haze",
    "hex": "#9F4576"
  },
  {
    "name": "Magenta-Rosa",
    "hex": "#CC338B"
  },
  {
    "name": "Magic Mint",
    "hex": "#AAF0D1"
  },
  {
    "name": "Magic Potion",
    "hex": "#FF4466"
  },
  {
    "name": "Magnolia",
    "hex": "#F8F4FF"
  },
  {
    "name": "Mahogany",
    "hex": "#C04000"
  },
  {
    "name": "Maize",
    "hex": "#FBEC5D"
  },
  {
    "name": "Majorelle Blau",
    "hex": "#6050DC"
  },
  {
    "name": "Malachite",
    "hex": "#0BDA51"
  },
  {
    "name": "Manatee",
    "hex": "#979AAA"
  },
  {
    "name": "Mandarin",
    "hex": "#F37A48"
  },
  {
    "name": "Mango Tango",
    "hex": "#FF8243"
  },
  {
    "name": "Mantis",
    "hex": "#74C365"
  },
  {
    "name": "Mardi Gras",
    "hex": "#880085"
  },
  {
    "name": "Marigold",
    "hex": "#EAA221"
  },
  {
    "name": "Kastanienbraun (Crayola)",
    "hex": "#C32148"
  },
  {
    "name": "Kastanienbraun (HTML/CSS)",
    "hex": "#800000"
  },
  {
    "name": "Kastanienbraun (X11)",
    "hex": "#B03060"
  },
  {
    "name": "Mauve",
    "hex": "#E0B0FF"
  },
  {
    "name": "Mauve Taupe",
    "hex": "#915F6D"
  },
  {
    "name": "Mauvelous",
    "hex": "#EF98AA"
  },
  {
    "name": "Maximum Blau",
    "hex": "#47ABCC"
  },
  {
    "name": "Maximum Blau Grün",
    "hex": "#30BFBF"
  },
  {
    "name": "Maximum Blau Lila",
    "hex": "#ACACE6"
  },
  {
    "name": "Maximum Grün",
    "hex": "#5E8C31"
  },
  {
    "name": "Maximum Grün Gelb",
    "hex": "#D9E650"
  },
  {
    "name": "Maximum Lila",
    "hex": "#733380"
  },
  {
    "name": "Maximum Rot",
    "hex": "#D92121"
  },
  {
    "name": "Maximum Rot Lila",
    "hex": "#A63A79"
  },
  {
    "name": "Maximum Gelb",
    "hex": "#FAFA37"
  },
  {
    "name": "Maximum Gelb Rot",
    "hex": "#F2BA49"
  },
  {
    "name": "May Grün",
    "hex": "#4C9141"
  },
  {
    "name": "Maya Blau",
    "hex": "#73C2FB"
  },
  {
    "name": "Meat Braun",
    "hex": "#E5B73B"
  },
  {
    "name": "Medium Aquamarine",
    "hex": "#66DDAA"
  },
  {
    "name": "Medium Blau",
    "hex": "#0000CD"
  },
  {
    "name": "Medium Candy Apple Rot",
    "hex": "#E2062C"
  },
  {
    "name": "Medium Carmine",
    "hex": "#AF4035"
  },
  {
    "name": "Medium Champagne",
    "hex": "#F3E5AB"
  },
  {
    "name": "Medium Electric Blau",
    "hex": "#035096"
  },
  {
    "name": "Medium Jungle Grün",
    "hex": "#1C352D"
  },
  {
    "name": "Medium Lavendel Magenta",
    "hex": "#DDA0DD"
  },
  {
    "name": "Medium Orchid",
    "hex": "#BA55D3"
  },
  {
    "name": "Medium Persian Blau",
    "hex": "#0067A5"
  },
  {
    "name": "Medium Lila",
    "hex": "#9370DB"
  },
  {
    "name": "Medium Rot-Violett",
    "hex": "#BB3385"
  },
  {
    "name": "Medium Rubin",
    "hex": "#AA4069"
  },
  {
    "name": "Medium Sea Grün",
    "hex": "#3CB371"
  },
  {
    "name": "Medium Sky Blau",
    "hex": "#80DAEB"
  },
  {
    "name": "Medium Slate Blau",
    "hex": "#7B68EE"
  },
  {
    "name": "Medium Spring Bud",
    "hex": "#C9DC87"
  },
  {
    "name": "Medium Spring Grün",
    "hex": "#00FA9A"
  },
  {
    "name": "Medium Taupe",
    "hex": "#674C47"
  },
  {
    "name": "Medium Türkis",
    "hex": "#48D1CC"
  },
  {
    "name": "Medium Tuscan Rot",
    "hex": "#79443B"
  },
  {
    "name": "Medium Vermilion",
    "hex": "#D9603B"
  },
  {
    "name": "Medium Violett-Rot",
    "hex": "#C71585"
  },
  {
    "name": "Mellow Apricot",
    "hex": "#F8B878"
  },
  {
    "name": "Mellow Gelb",
    "hex": "#F8DE7E"
  },
  {
    "name": "Melon",
    "hex": "#FDBCB4"
  },
  {
    "name": "Metallic Seaweed",
    "hex": "#0A7E8C"
  },
  {
    "name": "Metallic Sunburst",
    "hex": "#9C7C38"
  },
  {
    "name": "Mexican Rosa",
    "hex": "#E4007C"
  },
  {
    "name": "Middle Blau",
    "hex": "#7ED4E6"
  },
  {
    "name": "Middle Blau Grün",
    "hex": "#8DD9CC"
  },
  {
    "name": "Middle Blau Lila",
    "hex": "#8B72BE"
  },
  {
    "name": "Middle Rot Lila",
    "hex": "#210837"
  },
  {
    "name": "Middle Grün",
    "hex": "#4D8C57"
  },
  {
    "name": "Middle Grün Gelb",
    "hex": "#ACBF60"
  },
  {
    "name": "Middle Lila",
    "hex": "#D982B5"
  },
  {
    "name": "Middle Rot",
    "hex": "#E58E73"
  },
  {
    "name": "Middle Rot Lila",
    "hex": "#A55353"
  },
  {
    "name": "Middle Gelb",
    "hex": "#FFEB00"
  },
  {
    "name": "Middle Gelb Rot",
    "hex": "#ECB176"
  },
  {
    "name": "Midnight",
    "hex": "#702670"
  },
  {
    "name": "Midnight Blau",
    "hex": "#191970"
  },
  {
    "name": "Midnight Grün (Eagle Grün)",
    "hex": "#004953"
  },
  {
    "name": "Mikado Gelb",
    "hex": "#FFC40C"
  },
  {
    "name": "Milk",
    "hex": "#FDFFF5"
  },
  {
    "name": "Mimi Rosa",
    "hex": "#FFDAE9"
  },
  {
    "name": "Mindaro",
    "hex": "#E3F988"
  },
  {
    "name": "Ming",
    "hex": "#36747D"
  },
  {
    "name": "Minion Gelb",
    "hex": "#F5E050"
  },
  {
    "name": "Mint",
    "hex": "#3EB489"
  },
  {
    "name": "Mint Cream",
    "hex": "#F5FFFA"
  },
  {
    "name": "Mint Grün",
    "hex": "#98FF98"
  },
  {
    "name": "Misty Moss",
    "hex": "#BBB477"
  },
  {
    "name": "Misty Rose",
    "hex": "#FFE4E1"
  },
  {
    "name": "Moccasin",
    "hex": "#FAEBD7"
  },
  {
    "name": "Mode Beige",
    "hex": "#967117"
  },
  {
    "name": "Moonstone Blau",
    "hex": "#73A9C2"
  },
  {
    "name": "Mordant Rot 19",
    "hex": "#AE0C00"
  },
  {
    "name": "Morning Blau",
    "hex": "#8DA399"
  },
  {
    "name": "Moss Grün",
    "hex": "#8A9A5B"
  },
  {
    "name": "Mountain Meadow",
    "hex": "#30BA8F"
  },
  {
    "name": "Mountbatten Rosa",
    "hex": "#997A8D"
  },
  {
    "name": "MSU Grün",
    "hex": "#18453B"
  },
  {
    "name": "Mughal Grün",
    "hex": "#306030"
  },
  {
    "name": "Mulberry",
    "hex": "#C54B8C"
  },
  {
    "name": "Mummy's Tomb",
    "hex": "#828E84"
  },
  {
    "name": "Mustard",
    "hex": "#FFDB58"
  },
  {
    "name": "Myrtle Grün",
    "hex": "#317873"
  },
  {
    "name": "Mystic",
    "hex": "#D65282"
  },
  {
    "name": "Mystic Kastanienbraun",
    "hex": "#AD4379"
  },
  {
    "name": "Nadeshiko Rosa",
    "hex": "#F6ADC6"
  },
  {
    "name": "Napier Grün",
    "hex": "#2A8000"
  },
  {
    "name": "Naples Gelb",
    "hex": "#FADA5E"
  },
  {
    "name": "Navajo Weiß",
    "hex": "#FFDEAD"
  },
  {
    "name": "Navy",
    "hex": "#000080"
  },
  {
    "name": "Navy Lila",
    "hex": "#9457EB"
  },
  {
    "name": "Neon Carrot",
    "hex": "#FFA343"
  },
  {
    "name": "Neon Fuchsia",
    "hex": "#FE4164"
  },
  {
    "name": "Neon Grün",
    "hex": "#39FF14"
  },
  {
    "name": "New Car",
    "hex": "#214FC6"
  },
  {
    "name": "New York Rosa",
    "hex": "#D7837F"
  },
  {
    "name": "Nickel",
    "hex": "#727472"
  },
  {
    "name": "Non-Photo Blau",
    "hex": "#A4DDED"
  },
  {
    "name": "North Texas Grün",
    "hex": "#059033"
  },
  {
    "name": "Nyanza",
    "hex": "#E9FFDB"
  },
  {
    "name": "Ocean Blau",
    "hex": "#4F42B5"
  },
  {
    "name": "Ocean Boat Blau",
    "hex": "#0077BE"
  },
  {
    "name": "Ocean Grün",
    "hex": "#48BF91"
  },
  {
    "name": "Ochre",
    "hex": "#CC7722"
  },
  {
    "name": "Office Grün",
    "hex": "#008000"
  },
  {
    "name": "Ogre Odor",
    "hex": "#FD5240"
  },
  {
    "name": "Old Burgundy",
    "hex": "#43302E"
  },
  {
    "name": "Old Gold",
    "hex": "#CFB53B"
  },
  {
    "name": "Old Heliotrope",
    "hex": "#563C5C"
  },
  {
    "name": "Old Lace",
    "hex": "#FDF5E6"
  },
  {
    "name": "Old Lavendel",
    "hex": "#796878"
  },
  {
    "name": "Old Mauve",
    "hex": "#673147"
  },
  {
    "name": "Old Moss Grün",
    "hex": "#867E36"
  },
  {
    "name": "Old Rose",
    "hex": "#C08081"
  },
  {
    "name": "Old Silber",
    "hex": "#848482"
  },
  {
    "name": "Oliv",
    "hex": "#808000"
  },
  {
    "name": "Oliv Drab (#3)",
    "hex": "#6B8E23"
  },
  {
    "name": "Oliv Drab #7",
    "hex": "#3C341F"
  },
  {
    "name": "Olivine",
    "hex": "#9AB973"
  },
  {
    "name": "Onyx",
    "hex": "#353839"
  },
  {
    "name": "Opera Mauve",
    "hex": "#B784A7"
  },
  {
    "name": "Orange (Color Wheel)",
    "hex": "#FF7F00"
  },
  {
    "name": "Orange (Crayola)",
    "hex": "#FF7538"
  },
  {
    "name": "Orange (Pantone)",
    "hex": "#FF5800"
  },
  {
    "name": "Orange (RYB)",
    "hex": "#FB9902"
  },
  {
    "name": "Orange (Web)",
    "hex": "#FFA500"
  },
  {
    "name": "Orange Peel",
    "hex": "#FF9F00"
  },
  {
    "name": "Orange-Rot",
    "hex": "#FF4500"
  },
  {
    "name": "Orange Soda",
    "hex": "#FA5B3D"
  },
  {
    "name": "Orange-Gelb",
    "hex": "#F8D568"
  },
  {
    "name": "Orchid",
    "hex": "#DA70D6"
  },
  {
    "name": "Orchid Rosa",
    "hex": "#F2BDCD"
  },
  {
    "name": "Orioles Orange",
    "hex": "#FB4F14"
  },
  {
    "name": "Otter Braun",
    "hex": "#654321"
  },
  {
    "name": "Outer Space",
    "hex": "#414A4C"
  },
  {
    "name": "Outrageous Orange",
    "hex": "#FF6E4A"
  },
  {
    "name": "Oxford Blau",
    "hex": "#002147"
  },
  {
    "name": "OU Karmesin Rot",
    "hex": "#990000"
  },
  {
    "name": "Pacific Blau",
    "hex": "#1CA9C9"
  },
  {
    "name": "Pakistan Grün",
    "hex": "#006600"
  },
  {
    "name": "Palatinate Blau",
    "hex": "#273BE2"
  },
  {
    "name": "Palatinate Lila",
    "hex": "#682860"
  },
  {
    "name": "Blass Aqua",
    "hex": "#BCD4E6"
  },
  {
    "name": "Blass Blau",
    "hex": "#AFEEEE"
  },
  {
    "name": "Blass Braun",
    "hex": "#987654"
  },
  {
    "name": "Blass Carmine",
    "hex": "#AF4035"
  },
  {
    "name": "Blass Cerulean",
    "hex": "#9BC4E2"
  },
  {
    "name": "Blass Chestnut",
    "hex": "#DDADAF"
  },
  {
    "name": "Blass Kupfer",
    "hex": "#DA8A67"
  },
  {
    "name": "Blass Cornflower Blau",
    "hex": "#ABCDEF"
  },
  {
    "name": "Blass Cyan",
    "hex": "#87D3F8"
  },
  {
    "name": "Blass Gold",
    "hex": "#E6BE8A"
  },
  {
    "name": "Blass Goldenrod",
    "hex": "#EEE8AA"
  },
  {
    "name": "Blass Grün",
    "hex": "#98FB98"
  },
  {
    "name": "Blass Lavendel",
    "hex": "#DCD0FF"
  },
  {
    "name": "Blass Magenta",
    "hex": "#F984E5"
  },
  {
    "name": "Blass Magenta-Rosa",
    "hex": "#FF99CC"
  },
  {
    "name": "Blass Rosa",
    "hex": "#FADADD"
  },
  {
    "name": "Blass Plum",
    "hex": "#DDA0DD"
  },
  {
    "name": "Blass Rot-Violett",
    "hex": "#DB7093"
  },
  {
    "name": "Blass Robin Egg Blau",
    "hex": "#96DED1"
  },
  {
    "name": "Blass Silber",
    "hex": "#C9C0BB"
  },
  {
    "name": "Blass Spring Bud",
    "hex": "#ECEBBD"
  },
  {
    "name": "Blass Taupe",
    "hex": "#BC987E"
  },
  {
    "name": "Blass Türkis",
    "hex": "#AFEEEE"
  },
  {
    "name": "Blass Violett",
    "hex": "#CC99FF"
  },
  {
    "name": "Blass Violett-Rot",
    "hex": "#DB7093"
  },
  {
    "name": "Palm Leaf",
    "hex": "#6F9940"
  },
  {
    "name": "Pansy Lila",
    "hex": "#78184A"
  },
  {
    "name": "Paolo Veronese Grün",
    "hex": "#009B7D"
  },
  {
    "name": "Papaya Whip",
    "hex": "#FFEFD5"
  },
  {
    "name": "Paradise Rosa",
    "hex": "#E63E62"
  },
  {
    "name": "Paris Grün",
    "hex": "#50C878"
  },
  {
    "name": "Parrot Rosa",
    "hex": "#D998A0"
  },
  {
    "name": "Pastel Blau",
    "hex": "#AEC6CF"
  },
  {
    "name": "Pastel Braun",
    "hex": "#836953"
  },
  {
    "name": "Pastel Grau",
    "hex": "#CFCFC4"
  },
  {
    "name": "Pastel Grün",
    "hex": "#77DD77"
  },
  {
    "name": "Pastel Magenta",
    "hex": "#F49AC2"
  },
  {
    "name": "Pastel Orange",
    "hex": "#FFB347"
  },
  {
    "name": "Pastel Rosa",
    "hex": "#DEA5A4"
  },
  {
    "name": "Pastel Lila",
    "hex": "#B39EB5"
  },
  {
    "name": "Pastel Rot",
    "hex": "#FF6961"
  },
  {
    "name": "Pastel Violett",
    "hex": "#CB99C9"
  },
  {
    "name": "Pastel Gelb",
    "hex": "#FDFD96"
  },
  {
    "name": "Patriarch",
    "hex": "#800080"
  },
  {
    "name": "Payne's Grau",
    "hex": "#536878"
  },
  {
    "name": "Peach",
    "hex": "#FFE5B4"
  },
  {
    "name": "Peach",
    "hex": "#FFCBA4"
  },
  {
    "name": "Peach-Orange",
    "hex": "#FFCC99"
  },
  {
    "name": "Peach Puff",
    "hex": "#FFDAB9"
  },
  {
    "name": "Peach-Gelb",
    "hex": "#FADFAD"
  },
  {
    "name": "Pear",
    "hex": "#D1E231"
  },
  {
    "name": "Pearl",
    "hex": "#EAE0C8"
  },
  {
    "name": "Pearl Aqua",
    "hex": "#88D8C0"
  },
  {
    "name": "Pearly Lila",
    "hex": "#B768A2"
  },
  {
    "name": "Peridot",
    "hex": "#E6E200"
  },
  {
    "name": "Periwinkle",
    "hex": "#CCCCFF"
  },
  {
    "name": "Permanent Geranium Lake",
    "hex": "#E12C2C"
  },
  {
    "name": "Persian Blau",
    "hex": "#1C39BB"
  },
  {
    "name": "Persian Grün",
    "hex": "#00A693"
  },
  {
    "name": "Persian Indigo",
    "hex": "#32127A"
  },
  {
    "name": "Persian Orange",
    "hex": "#D99058"
  },
  {
    "name": "Persian Rosa",
    "hex": "#F77FBE"
  },
  {
    "name": "Persian Plum",
    "hex": "#701C1C"
  },
  {
    "name": "Persian Rot",
    "hex": "#CC3333"
  },
  {
    "name": "Persian Rose",
    "hex": "#FE28A2"
  },
  {
    "name": "Persimmon",
    "hex": "#EC5800"
  },
  {
    "name": "Peru",
    "hex": "#CD853F"
  },
  {
    "name": "Pewter Blau",
    "hex": "#8BA8B7"
  },
  {
    "name": "Phlox",
    "hex": "#DF00FF"
  },
  {
    "name": "Phthalo Blau",
    "hex": "#000F89"
  },
  {
    "name": "Phthalo Grün",
    "hex": "#123524"
  },
  {
    "name": "Picton Blau",
    "hex": "#45B1E8"
  },
  {
    "name": "Pictorial Carmine",
    "hex": "#C30B4E"
  },
  {
    "name": "Piggy Rosa",
    "hex": "#FDDDE6"
  },
  {
    "name": "Pine Grün",
    "hex": "#01796F"
  },
  {
    "name": "Pineapple",
    "hex": "#563C0D"
  },
  {
    "name": "Rosa",
    "hex": "#FFC0CB"
  },
  {
    "name": "Rosa (Pantone)",
    "hex": "#D74894"
  },
  {
    "name": "Rosa Flamingo",
    "hex": "#FC74FD"
  },
  {
    "name": "Rosa Lace",
    "hex": "#FFDDF4"
  },
  {
    "name": "Rosa Lavendel",
    "hex": "#D8B2D1"
  },
  {
    "name": "Rosa-Orange",
    "hex": "#FF9966"
  },
  {
    "name": "Rosa Pearl",
    "hex": "#E7ACCF"
  },
  {
    "name": "Rosa Raspberry",
    "hex": "#980036"
  },
  {
    "name": "Rosa Sherbet",
    "hex": "#F78FA7"
  },
  {
    "name": "Pistachio",
    "hex": "#93C572"
  },
  {
    "name": "Pixie Powder",
    "hex": "#391285"
  },
  {
    "name": "Platinum",
    "hex": "#E5E4E2"
  },
  {
    "name": "Plum",
    "hex": "#8E4585"
  },
  {
    "name": "Plum (Web)",
    "hex": "#DDA0DD"
  },
  {
    "name": "Plump Lila",
    "hex": "#5946B2"
  },
  {
    "name": "Polished Pine",
    "hex": "#5DA493"
  },
  {
    "name": "Pomp And Power",
    "hex": "#86608E"
  },
  {
    "name": "Popstar",
    "hex": "#BE4F62"
  },
  {
    "name": "Portland Orange",
    "hex": "#FF5A36"
  },
  {
    "name": "Powder Blau",
    "hex": "#B0E0E6"
  },
  {
    "name": "Princess Perfume",
    "hex": "#FF85CF"
  },
  {
    "name": "Princeton Orange",
    "hex": "#F58025"
  },
  {
    "name": "Prune",
    "hex": "#701C1C"
  },
  {
    "name": "Prussian Blau",
    "hex": "#003153"
  },
  {
    "name": "Psychedelic Lila",
    "hex": "#DF00FF"
  },
  {
    "name": "Puce",
    "hex": "#CC8899"
  },
  {
    "name": "Puce Rot",
    "hex": "#722F37"
  },
  {
    "name": "Pullman Braun (UPS Braun)",
    "hex": "#644117"
  },
  {
    "name": "Pullman Grün",
    "hex": "#3B331C"
  },
  {
    "name": "Pumpkin",
    "hex": "#FF7518"
  },
  {
    "name": "Lila (HTML)",
    "hex": "#800080"
  },
  {
    "name": "Lila (Munsell)",
    "hex": "#9F00C5"
  },
  {
    "name": "Lila (X11)",
    "hex": "#A020F0"
  },
  {
    "name": "Lila Heart",
    "hex": "#69359C"
  },
  {
    "name": "Lila Mountain Majesty",
    "hex": "#9678B6"
  },
  {
    "name": "Lila Navy",
    "hex": "#4E5180"
  },
  {
    "name": "Lila Pizzazz",
    "hex": "#FE4EDA"
  },
  {
    "name": "Lila Plum",
    "hex": "#9C51B6"
  },
  {
    "name": "Lila Taupe",
    "hex": "#50404D"
  },
  {
    "name": "Purpureus",
    "hex": "#9A4EAE"
  },
  {
    "name": "Quartz",
    "hex": "#51484F"
  },
  {
    "name": "Queen Blau",
    "hex": "#436B95"
  },
  {
    "name": "Queen Rosa",
    "hex": "#E8CCD7"
  },
  {
    "name": "Quick Silber",
    "hex": "#A6A6A6"
  },
  {
    "name": "Quinacridone Magenta",
    "hex": "#8E3A59"
  },
  {
    "name": "Rackley",
    "hex": "#5D8AA8"
  },
  {
    "name": "Radical Rot",
    "hex": "#FF355E"
  },
  {
    "name": "Raisin Schwarz",
    "hex": "#242124"
  },
  {
    "name": "Rajah",
    "hex": "#FBAB60"
  },
  {
    "name": "Raspberry",
    "hex": "#E30B5D"
  },
  {
    "name": "Raspberry Glace",
    "hex": "#915F6D"
  },
  {
    "name": "Raspberry Rosa",
    "hex": "#E25098"
  },
  {
    "name": "Raspberry Rose",
    "hex": "#B3446C"
  },
  {
    "name": "Raw Sienna",
    "hex": "#D68A59"
  },
  {
    "name": "Raw Umber",
    "hex": "#826644"
  },
  {
    "name": "Razzle Dazzle Rose",
    "hex": "#FF33CC"
  },
  {
    "name": "Razzmatazz",
    "hex": "#E3256B"
  },
  {
    "name": "Razzmic Berry",
    "hex": "#8D4E85"
  },
  {
    "name": "Rebecca Lila",
    "hex": "#663399"
  },
  {
    "name": "Rot",
    "hex": "#FF0000"
  },
  {
    "name": "Rot (Crayola)",
    "hex": "#EE204D"
  },
  {
    "name": "Rot (Munsell)",
    "hex": "#F2003C"
  },
  {
    "name": "Rot (NCS)",
    "hex": "#C40233"
  },
  {
    "name": "Rot (Pantone)",
    "hex": "#ED2939"
  },
  {
    "name": "Rot (Pigment)",
    "hex": "#ED1C24"
  },
  {
    "name": "Rot (RYB)",
    "hex": "#FE2712"
  },
  {
    "name": "Rot-Braun",
    "hex": "#A52A2A"
  },
  {
    "name": "Rot Devil",
    "hex": "#860111"
  },
  {
    "name": "Rot-Orange",
    "hex": "#FF5349"
  },
  {
    "name": "Rot-Lila",
    "hex": "#E40078"
  },
  {
    "name": "Rot Salsa",
    "hex": "#FD3A4A"
  },
  {
    "name": "Rot-Violett",
    "hex": "#C71585"
  },
  {
    "name": "Redwood",
    "hex": "#A45A52"
  },
  {
    "name": "Regalia",
    "hex": "#522D80"
  },
  {
    "name": "Registration Schwarz",
    "hex": "#000000"
  },
  {
    "name": "Resolution Blau",
    "hex": "#002387"
  },
  {
    "name": "Rhythm",
    "hex": "#777696"
  },
  {
    "name": "Satt Schwarz",
    "hex": "#004040"
  },
  {
    "name": "Satt Schwarz (FOGRA29)",
    "hex": "#010B13"
  },
  {
    "name": "Satt Schwarz (FOGRA39)",
    "hex": "#010203"
  },
  {
    "name": "Satt Brilliant Lavendel",
    "hex": "#F1A7FE"
  },
  {
    "name": "Satt Carmine",
    "hex": "#D70040"
  },
  {
    "name": "Satt Electric Blau",
    "hex": "#0892D0"
  },
  {
    "name": "Satt Lavendel",
    "hex": "#A76BCF"
  },
  {
    "name": "Satt Lilac",
    "hex": "#B666D2"
  },
  {
    "name": "Satt Kastanienbraun",
    "hex": "#B03060"
  },
  {
    "name": "Rifle Grün",
    "hex": "#444C38"
  },
  {
    "name": "Roast Coffee",
    "hex": "#704241"
  },
  {
    "name": "Robin Egg Blau",
    "hex": "#00CCCC"
  },
  {
    "name": "Rocket Metallic",
    "hex": "#8A7F80"
  },
  {
    "name": "Roman Silber",
    "hex": "#838996"
  },
  {
    "name": "Rose",
    "hex": "#FF007F"
  },
  {
    "name": "Rose Bonbon",
    "hex": "#F9429E"
  },
  {
    "name": "Rose Dust",
    "hex": "#9E5E6F"
  },
  {
    "name": "Rose Ebony",
    "hex": "#674846"
  },
  {
    "name": "Rose Gold",
    "hex": "#B76E79"
  },
  {
    "name": "Rose Madder",
    "hex": "#E32636"
  },
  {
    "name": "Rose Rosa",
    "hex": "#FF66CC"
  },
  {
    "name": "Rose Quartz",
    "hex": "#AA98A9"
  },
  {
    "name": "Rose Rot",
    "hex": "#C21E56"
  },
  {
    "name": "Rose Taupe",
    "hex": "#905D5D"
  },
  {
    "name": "Rose Vale",
    "hex": "#AB4E52"
  },
  {
    "name": "Rosewood",
    "hex": "#65000B"
  },
  {
    "name": "Rosso Corsa",
    "hex": "#D40000"
  },
  {
    "name": "Rosy Braun",
    "hex": "#BC8F8F"
  },
  {
    "name": "Royal Azur",
    "hex": "#0038A8"
  },
  {
    "name": "Royal Blau",
    "hex": "#002366"
  },
  {
    "name": "Royal Blau",
    "hex": "#4169E1"
  },
  {
    "name": "Royal Fuchsia",
    "hex": "#CA2C92"
  },
  {
    "name": "Royal Lila",
    "hex": "#7851A9"
  },
  {
    "name": "Royal Gelb",
    "hex": "#FADA5E"
  },
  {
    "name": "Ruber",
    "hex": "#CE4676"
  },
  {
    "name": "Rubine Rot",
    "hex": "#D10056"
  },
  {
    "name": "Rubin",
    "hex": "#E0115F"
  },
  {
    "name": "Rubin Rot",
    "hex": "#9B111E"
  },
  {
    "name": "Ruddy",
    "hex": "#FF0028"
  },
  {
    "name": "Ruddy Braun",
    "hex": "#BB6528"
  },
  {
    "name": "Ruddy Rosa",
    "hex": "#E18E96"
  },
  {
    "name": "Rufous",
    "hex": "#A81C07"
  },
  {
    "name": "Russet",
    "hex": "#80461B"
  },
  {
    "name": "Russian Grün",
    "hex": "#679267"
  },
  {
    "name": "Russian Violett",
    "hex": "#32174D"
  },
  {
    "name": "Rust",
    "hex": "#B7410E"
  },
  {
    "name": "Rusty Rot",
    "hex": "#DA2C43"
  },
  {
    "name": "Sacramento State Grün",
    "hex": "#00563F"
  },
  {
    "name": "Saddle Braun",
    "hex": "#8B4513"
  },
  {
    "name": "Safety Orange",
    "hex": "#FF7800"
  },
  {
    "name": "Safety Orange (Blaze Orange)",
    "hex": "#FF6700"
  },
  {
    "name": "Safety Gelb",
    "hex": "#EED202"
  },
  {
    "name": "Saffron",
    "hex": "#F4C430"
  },
  {
    "name": "Sage",
    "hex": "#BCB88A"
  },
  {
    "name": "St. Patrick's Blau",
    "hex": "#23297A"
  },
  {
    "name": "Salmon",
    "hex": "#FA8072"
  },
  {
    "name": "Salmon Rosa",
    "hex": "#FF91A4"
  },
  {
    "name": "Sand",
    "hex": "#C2B280"
  },
  {
    "name": "Sand Dune",
    "hex": "#967117"
  },
  {
    "name": "Sandstorm",
    "hex": "#ECD540"
  },
  {
    "name": "Sandy Braun",
    "hex": "#F4A460"
  },
  {
    "name": "Sandy Tan",
    "hex": "#FDD9B5"
  },
  {
    "name": "Sandy Taupe",
    "hex": "#967117"
  },
  {
    "name": "Sangria",
    "hex": "#92000A"
  },
  {
    "name": "Sap Grün",
    "hex": "#507D2A"
  },
  {
    "name": "Saphir",
    "hex": "#0F52BA"
  },
  {
    "name": "Saphir Blau",
    "hex": "#0067A5"
  },
  {
    "name": "Sasquatch Socks",
    "hex": "#FF4681"
  },
  {
    "name": "Satin Sheen Gold",
    "hex": "#CBA135"
  },
  {
    "name": "Scharlach",
    "hex": "#FF2400"
  },
  {
    "name": "Scharlach",
    "hex": "#FD0E35"
  },
  {
    "name": "Schauss Rosa",
    "hex": "#FF91AF"
  },
  {
    "name": "School Bus Gelb",
    "hex": "#FFD800"
  },
  {
    "name": "Screamin' Grün",
    "hex": "#66FF66"
  },
  {
    "name": "Sea Blau",
    "hex": "#006994"
  },
  {
    "name": "Sea Foam Grün",
    "hex": "#9FE2BF"
  },
  {
    "name": "Sea Grün",
    "hex": "#2E8B57"
  },
  {
    "name": "Sea Serpent",
    "hex": "#4BC7CF"
  },
  {
    "name": "Seal Braun",
    "hex": "#59260B"
  },
  {
    "name": "Seashell",
    "hex": "#FFF5EE"
  },
  {
    "name": "Selective Gelb",
    "hex": "#FFBA00"
  },
  {
    "name": "Sepia",
    "hex": "#704214"
  },
  {
    "name": "Shadow",
    "hex": "#8A795D"
  },
  {
    "name": "Shadow Blau",
    "hex": "#778BA5"
  },
  {
    "name": "Shampoo",
    "hex": "#FFCFF1"
  },
  {
    "name": "Shamrock Grün",
    "hex": "#009E60"
  },
  {
    "name": "Sheen Grün",
    "hex": "#8FD400"
  },
  {
    "name": "Shimmering Blush",
    "hex": "#D98695"
  },
  {
    "name": "Shiny Shamrock",
    "hex": "#5FA778"
  },
  {
    "name": "Shocking Rosa",
    "hex": "#FC0FC0"
  },
  {
    "name": "Shocking Rosa (Crayola)",
    "hex": "#FF6FFF"
  },
  {
    "name": "Sienna",
    "hex": "#882D17"
  },
  {
    "name": "Silber",
    "hex": "#C0C0C0"
  },
  {
    "name": "Silber Chalice",
    "hex": "#ACACAC"
  },
  {
    "name": "Silber Lake Blau",
    "hex": "#5D89BA"
  },
  {
    "name": "Silber Rosa",
    "hex": "#C4AEAD"
  },
  {
    "name": "Silber Sand",
    "hex": "#BFC1C2"
  },
  {
    "name": "Sinopia",
    "hex": "#CB410B"
  },
  {
    "name": "Sizzling Rot",
    "hex": "#FF3855"
  },
  {
    "name": "Sizzling Sunrise",
    "hex": "#FFDB00"
  },
  {
    "name": "Skobeloff",
    "hex": "#007474"
  },
  {
    "name": "Sky Blau",
    "hex": "#87CEEB"
  },
  {
    "name": "Sky Magenta",
    "hex": "#CF71AF"
  },
  {
    "name": "Slate Blau",
    "hex": "#6A5ACD"
  },
  {
    "name": "Slate Grau",
    "hex": "#708090"
  },
  {
    "name": "Smalt (Dunkel Powder Blau)",
    "hex": "#003399"
  },
  {
    "name": "Slimy Grün",
    "hex": "#299617"
  },
  {
    "name": "Smashed Pumpkin",
    "hex": "#FF6D3A"
  },
  {
    "name": "Smitten",
    "hex": "#C84186"
  },
  {
    "name": "Smoke",
    "hex": "#738276"
  },
  {
    "name": "Smokey Topaz",
    "hex": "#832A0D"
  },
  {
    "name": "Smoky Schwarz",
    "hex": "#100C08"
  },
  {
    "name": "Smoky Topaz",
    "hex": "#933D41"
  },
  {
    "name": "Snow",
    "hex": "#FFFAFA"
  },
  {
    "name": "Soap",
    "hex": "#CEC8EF"
  },
  {
    "name": "Solid Rosa",
    "hex": "#893843"
  },
  {
    "name": "Sonic Silber",
    "hex": "#757575"
  },
  {
    "name": "Spartan Karmesin",
    "hex": "#9E1316"
  },
  {
    "name": "Space Cadet",
    "hex": "#1D2951"
  },
  {
    "name": "Spanish Bistre",
    "hex": "#807532"
  },
  {
    "name": "Spanish Blau",
    "hex": "#0070B8"
  },
  {
    "name": "Spanish Carmine",
    "hex": "#D10047"
  },
  {
    "name": "Spanish Karmesin",
    "hex": "#E51A4C"
  },
  {
    "name": "Spanish Grau",
    "hex": "#989898"
  },
  {
    "name": "Spanish Grün",
    "hex": "#009150"
  },
  {
    "name": "Spanish Orange",
    "hex": "#E86100"
  },
  {
    "name": "Spanish Rosa",
    "hex": "#F7BFBE"
  },
  {
    "name": "Spanish Rot",
    "hex": "#E60026"
  },
  {
    "name": "Spanish Sky Blau",
    "hex": "#00FFFF"
  },
  {
    "name": "Spanish Violett",
    "hex": "#4C2882"
  },
  {
    "name": "Spanish Viridian",
    "hex": "#007F5C"
  },
  {
    "name": "Spicy Mix",
    "hex": "#8B5f4D"
  },
  {
    "name": "Spiro Disco Ball",
    "hex": "#0FC0FC"
  },
  {
    "name": "Spring Bud",
    "hex": "#A7FC00"
  },
  {
    "name": "Spring Frost",
    "hex": "#87FF2A"
  },
  {
    "name": "Spring Grün",
    "hex": "#00FF7F"
  },
  {
    "name": "Star Command Blau",
    "hex": "#007BB8"
  },
  {
    "name": "Steel Blau",
    "hex": "#4682B4"
  },
  {
    "name": "Steel Rosa",
    "hex": "#CC33CC"
  },
  {
    "name": "Steel Blaugrün",
    "hex": "#5F8A8B"
  },
  {
    "name": "Stil De Grain Gelb",
    "hex": "#FADA5E"
  },
  {
    "name": "Stizza",
    "hex": "#990000"
  },
  {
    "name": "Stormcloud",
    "hex": "#4F666A"
  },
  {
    "name": "Straw",
    "hex": "#E4D96F"
  },
  {
    "name": "Strawberry",
    "hex": "#FC5A8D"
  },
  {
    "name": "Sugar Plum",
    "hex": "#914E75"
  },
  {
    "name": "Sunburnt Cyclops",
    "hex": "#FF404C"
  },
  {
    "name": "Sunglow",
    "hex": "#FFCC33"
  },
  {
    "name": "Sunny",
    "hex": "#F2F27A"
  },
  {
    "name": "Sunray",
    "hex": "#E3AB57"
  },
  {
    "name": "Sunset",
    "hex": "#FAD6A5"
  },
  {
    "name": "Sunset Orange",
    "hex": "#FD5E53"
  },
  {
    "name": "Super Rosa",
    "hex": "#CF6BA9"
  },
  {
    "name": "Sweet Braun",
    "hex": "#A83731"
  },
  {
    "name": "Tan",
    "hex": "#D2B48C"
  },
  {
    "name": "Tangelo",
    "hex": "#F94D00"
  },
  {
    "name": "Tangerine",
    "hex": "#F28500"
  },
  {
    "name": "Tangerine Gelb",
    "hex": "#FFCC00"
  },
  {
    "name": "Tango Rosa",
    "hex": "#E4717A"
  },
  {
    "name": "Tart Orange",
    "hex": "#FB4D46"
  },
  {
    "name": "Taupe",
    "hex": "#483C32"
  },
  {
    "name": "Taupe Grau",
    "hex": "#8B8589"
  },
  {
    "name": "Tea Grün",
    "hex": "#D0F0C0"
  },
  {
    "name": "Tea Rose",
    "hex": "#F88379"
  },
  {
    "name": "Tea Rose",
    "hex": "#F4C2C2"
  },
  {
    "name": "Blaugrün",
    "hex": "#008080"
  },
  {
    "name": "Blaugrün Blau",
    "hex": "#367588"
  },
  {
    "name": "Blaugrün Deer",
    "hex": "#99E6B3"
  },
  {
    "name": "Blaugrün Grün",
    "hex": "#00827F"
  },
  {
    "name": "Telemagenta",
    "hex": "#CF3476"
  },
  {
    "name": "Tenne (Tawny)",
    "hex": "#CD5700"
  },
  {
    "name": "Terra Cotta",
    "hex": "#E2725B"
  },
  {
    "name": "Thistle",
    "hex": "#D8BFD8"
  },
  {
    "name": "Thulian Rosa",
    "hex": "#DE6FA1"
  },
  {
    "name": "Tickle Me Rosa",
    "hex": "#FC89AC"
  },
  {
    "name": "Tiffany Blau",
    "hex": "#0ABAB5"
  },
  {
    "name": "Tiger's Eye",
    "hex": "#E08D3C"
  },
  {
    "name": "Timberwolf",
    "hex": "#DBD7D2"
  },
  {
    "name": "Titanium Gelb",
    "hex": "#EEE600"
  },
  {
    "name": "Tomato",
    "hex": "#FF6347"
  },
  {
    "name": "Toolbox",
    "hex": "#746CC0"
  },
  {
    "name": "Topaz",
    "hex": "#FFC87C"
  },
  {
    "name": "Tractor Rot",
    "hex": "#FD0E35"
  },
  {
    "name": "Trolley Grau",
    "hex": "#808080"
  },
  {
    "name": "Tropical Rain Forest",
    "hex": "#00755E"
  },
  {
    "name": "Tropical Violett",
    "hex": "#CDA4DE"
  },
  {
    "name": "True Blau",
    "hex": "#0073CF"
  },
  {
    "name": "Tufts Blau",
    "hex": "#3E8EDE"
  },
  {
    "name": "Tulip",
    "hex": "#FF878D"
  },
  {
    "name": "Tumbleweed",
    "hex": "#DEAA88"
  },
  {
    "name": "Turkish Rose",
    "hex": "#B57281"
  },
  {
    "name": "Türkis",
    "hex": "#40E0D0"
  },
  {
    "name": "Türkis Blau",
    "hex": "#00FFEF"
  },
  {
    "name": "Türkis Grün",
    "hex": "#A0D6B4"
  },
  {
    "name": "Türkis Surf",
    "hex": "#00C5CD"
  },
  {
    "name": "Turtle Grün",
    "hex": "#8A9A5B"
  },
  {
    "name": "Tuscan",
    "hex": "#FAD6A5"
  },
  {
    "name": "Tuscan Braun",
    "hex": "#6F4E37"
  },
  {
    "name": "Tuscan Rot",
    "hex": "#7C4848"
  },
  {
    "name": "Tuscan Tan",
    "hex": "#A67B5B"
  },
  {
    "name": "Tuscany",
    "hex": "#C09999"
  },
  {
    "name": "Twilight Lavendel",
    "hex": "#8A496B"
  },
  {
    "name": "Tyrian Lila",
    "hex": "#66023C"
  },
  {
    "name": "UA Blau",
    "hex": "#0033AA"
  },
  {
    "name": "UA Rot",
    "hex": "#D9004C"
  },
  {
    "name": "Ube",
    "hex": "#8878C3"
  },
  {
    "name": "UCLA Blau",
    "hex": "#536895"
  },
  {
    "name": "UCLA Gold",
    "hex": "#FFB300"
  },
  {
    "name": "UFO Grün",
    "hex": "#3CD070"
  },
  {
    "name": "Ultramarine",
    "hex": "#3F00FF"
  },
  {
    "name": "Ultramarine Blau",
    "hex": "#4166F5"
  },
  {
    "name": "Ultra Rosa",
    "hex": "#FF6FFF"
  },
  {
    "name": "Ultra Rot",
    "hex": "#FC6C85"
  },
  {
    "name": "Umber",
    "hex": "#635147"
  },
  {
    "name": "Unbleached Silk",
    "hex": "#FFDDCA"
  },
  {
    "name": "United Nations Blau",
    "hex": "#5B92E5"
  },
  {
    "name": "University Of California Gold",
    "hex": "#B78727"
  },
  {
    "name": "Unmellow Gelb",
    "hex": "#FFFF66"
  },
  {
    "name": "UP Forest Grün",
    "hex": "#014421"
  },
  {
    "name": "UP Kastanienbraun",
    "hex": "#7B1113"
  },
  {
    "name": "Upsdell Rot",
    "hex": "#AE2029"
  },
  {
    "name": "Urobilin",
    "hex": "#E1AD21"
  },
  {
    "name": "USAFA Blau",
    "hex": "#004F98"
  },
  {
    "name": "USC Cardinal",
    "hex": "#990000"
  },
  {
    "name": "USC Gold",
    "hex": "#FFCC00"
  },
  {
    "name": "University Of Tennessee Orange",
    "hex": "#F77F00"
  },
  {
    "name": "Utah Karmesin",
    "hex": "#D3003F"
  },
  {
    "name": "Van Dyke Braun",
    "hex": "#664228"
  },
  {
    "name": "Vanilla",
    "hex": "#F3E5AB"
  },
  {
    "name": "Vanilla Ice",
    "hex": "#F38FA9"
  },
  {
    "name": "Vegas Gold",
    "hex": "#C5B358"
  },
  {
    "name": "Venetian Rot",
    "hex": "#C80815"
  },
  {
    "name": "Verdigris",
    "hex": "#43B3AE"
  },
  {
    "name": "Vermilion",
    "hex": "#E34234"
  },
  {
    "name": "Vermilion",
    "hex": "#D9381E"
  },
  {
    "name": "Veronica",
    "hex": "#A020F0"
  },
  {
    "name": "Very Hell Azur",
    "hex": "#74BBFB"
  },
  {
    "name": "Very Hell Blau",
    "hex": "#6666FF"
  },
  {
    "name": "Very Hell Malachite Grün",
    "hex": "#64E986"
  },
  {
    "name": "Very Hell Tangelo",
    "hex": "#FFB077"
  },
  {
    "name": "Very Blass Orange",
    "hex": "#FFDFBF"
  },
  {
    "name": "Very Blass Gelb",
    "hex": "#FFFFBF"
  },
  {
    "name": "Violett",
    "hex": "#8F00FF"
  },
  {
    "name": "Violett (Color Wheel)",
    "hex": "#7F00FF"
  },
  {
    "name": "Violett (RYB)",
    "hex": "#8601AF"
  },
  {
    "name": "Violett (Web)",
    "hex": "#EE82EE"
  },
  {
    "name": "Violett-Blau",
    "hex": "#324AB2"
  },
  {
    "name": "Violett-Rot",
    "hex": "#F75394"
  },
  {
    "name": "Viridian",
    "hex": "#40826D"
  },
  {
    "name": "Viridian Grün",
    "hex": "#009698"
  },
  {
    "name": "Vista Blau",
    "hex": "#7C9ED9"
  },
  {
    "name": "Lebhaft Amber",
    "hex": "#CC9900"
  },
  {
    "name": "Lebhaft Auburn",
    "hex": "#922724"
  },
  {
    "name": "Lebhaft Burgundy",
    "hex": "#9F1D35"
  },
  {
    "name": "Lebhaft Cerise",
    "hex": "#DA1D81"
  },
  {
    "name": "Lebhaft Cerulean",
    "hex": "#00AAEE"
  },
  {
    "name": "Lebhaft Karmesin",
    "hex": "#CC0033"
  },
  {
    "name": "Lebhaft Gamboge",
    "hex": "#FF9900"
  },
  {
    "name": "Lebhaft Lime Grün",
    "hex": "#A6D608"
  },
  {
    "name": "Lebhaft Malachite",
    "hex": "#00CC33"
  },
  {
    "name": "Lebhaft Mulberry",
    "hex": "#B80CE3"
  },
  {
    "name": "Lebhaft Orange",
    "hex": "#FF5F00"
  },
  {
    "name": "Lebhaft Orange Peel",
    "hex": "#FFA000"
  },
  {
    "name": "Lebhaft Orchid",
    "hex": "#CC00FF"
  },
  {
    "name": "Lebhaft Raspberry",
    "hex": "#FF006C"
  },
  {
    "name": "Lebhaft Rot",
    "hex": "#F70D1A"
  },
  {
    "name": "Lebhaft Rot-Tangelo",
    "hex": "#DF6124"
  },
  {
    "name": "Lebhaft Sky Blau",
    "hex": "#00CCFF"
  },
  {
    "name": "Lebhaft Tangelo",
    "hex": "#F07427"
  },
  {
    "name": "Lebhaft Tangerine",
    "hex": "#FFA089"
  },
  {
    "name": "Lebhaft Vermilion",
    "hex": "#E56024"
  },
  {
    "name": "Lebhaft Violett",
    "hex": "#9F00FF"
  },
  {
    "name": "Lebhaft Gelb",
    "hex": "#FFE302"
  },
  {
    "name": "Volt",
    "hex": "#CEFF00"
  },
  {
    "name": "Wageningen Grün",
    "hex": "#34B233"
  },
  {
    "name": "Warm Schwarz",
    "hex": "#004242"
  },
  {
    "name": "Waterspout",
    "hex": "#A4F4F9"
  },
  {
    "name": "Weldon Blau",
    "hex": "#7C98AB"
  },
  {
    "name": "Wenge",
    "hex": "#645452"
  },
  {
    "name": "Wheat",
    "hex": "#F5DEB3"
  },
  {
    "name": "Weiß",
    "hex": "#FFFFFF"
  },
  {
    "name": "Weiß Smoke",
    "hex": "#F5F5F5"
  },
  {
    "name": "Wild Blau Yonder",
    "hex": "#A2ADD0"
  },
  {
    "name": "Wild Orchid",
    "hex": "#D470A2"
  },
  {
    "name": "Wild Strawberry",
    "hex": "#FF43A4"
  },
  {
    "name": "Wild Watermelon",
    "hex": "#FC6C85"
  },
  {
    "name": "Willpower Orange",
    "hex": "#FD5800"
  },
  {
    "name": "Windsor Tan",
    "hex": "#A75502"
  },
  {
    "name": "Wine",
    "hex": "#722F37"
  },
  {
    "name": "Wine Dregs",
    "hex": "#673147"
  },
  {
    "name": "Winter Sky",
    "hex": "#FF007C"
  },
  {
    "name": "Winter Wizard",
    "hex": "#A0E6FF"
  },
  {
    "name": "Wintergreen Dream",
    "hex": "#56887D"
  },
  {
    "name": "Wisteria",
    "hex": "#C9A0DC"
  },
  {
    "name": "Wood Braun",
    "hex": "#C19A6B"
  },
  {
    "name": "Xanadu",
    "hex": "#738678"
  },
  {
    "name": "Yale Blau",
    "hex": "#0F4D92"
  },
  {
    "name": "Yankees Blau",
    "hex": "#1C2841"
  },
  {
    "name": "Gelb",
    "hex": "#FFFF00"
  },
  {
    "name": "Gelb (Crayola)",
    "hex": "#FCE883"
  },
  {
    "name": "Gelb (Munsell)",
    "hex": "#EFCC00"
  },
  {
    "name": "Gelb (NCS)",
    "hex": "#FFD300"
  },
  {
    "name": "Gelb (Pantone)",
    "hex": "#FEDF00"
  },
  {
    "name": "Gelb (Process)",
    "hex": "#FFEF00"
  },
  {
    "name": "Gelb (RYB)",
    "hex": "#FEFE33"
  },
  {
    "name": "Gelb-Grün",
    "hex": "#9ACD32"
  },
  {
    "name": "Gelb Orange",
    "hex": "#FFAE42"
  },
  {
    "name": "Gelb Rose",
    "hex": "#FFF000"
  },
  {
    "name": "Gelb Sunshine",
    "hex": "#FFF700"
  },
  {
    "name": "Zaffre",
    "hex": "#0014A8"
  },
  {
    "name": "Zinnwaldite Braun",
    "hex": "#2C1608"
  },
  {
    "name": "Zomp",
    "hex": "#39A78E"
  }
]
